[
  {
    "id": 1,
    "mode": 1,
    "levelMax": 1,
    "chapter": 1,
    "levelMin": 1,
    "ammoCount": 5,
    "tripleStar": 1,
    "doubleStar": 2,
    "singleStar": 3,
    "sceneId": 1
  },
  {
    "id": 2,
    "mode": 1,
    "levelMax": 1,
    "chapter": 1,
    "levelMin": 2,
    "ammoCount": 5,
    "tripleStar": 1,
    "doubleStar": 2,
    "singleStar": 3,
    "sceneId": 2
  },
  {
    "id": 3,
    "mode": 1,
    "levelMax": 1,
    "chapter": 1,
    "levelMin": 3,
    "ammoCount": 5,
    "tripleStar": 1,
    "doubleStar": 2,
    "singleStar": 3,
    "sceneId": 3
  },
  {
    "id": 4,
    "mode": 1,
    "levelMax": 1,
    "chapter": 1,
    "levelMin": 4,
    "ammoCount": 6,
    "tripleStar": 2,
    "doubleStar": 3,
    "singleStar": 4,
    "sceneId": 4
  },
  {
    "id": 5,
    "mode": 1,
    "levelMax": 1,
    "chapter": 1,
    "levelMin": 5,
    "ammoCount": 6,
    "tripleStar": 2,
    "doubleStar": 3,
    "singleStar": 4,
    "sceneId": 5
  },
  {
    "id": 6,
    "mode": 1,
    "levelMax": 1,
    "chapter": 1,
    "levelMin": 6,
    "ammoCount": 6,
    "tripleStar": 2,
    "doubleStar": 3,
    "singleStar": 4,
    "sceneId": 6
  },
  {
    "id": 7,
    "mode": 1,
    "levelMax": 1,
    "chapter": 1,
    "levelMin": 7,
    "ammoCount": 5,
    "tripleStar": 1,
    "doubleStar": 2,
    "singleStar": 3,
    "sceneId": 7
  },
  {
    "id": 8,
    "mode": 1,
    "levelMax": 1,
    "chapter": 1,
    "levelMin": 8,
    "ammoCount": 8,
    "tripleStar": 4,
    "doubleStar": 5,
    "singleStar": 6,
    "sceneId": 8
  },
  {
    "id": 9,
    "mode": 1,
    "levelMax": 1,
    "chapter": 1,
    "levelMin": 9,
    "ammoCount": 6,
    "tripleStar": 2,
    "doubleStar": 3,
    "singleStar": 4,
    "sceneId": 9
  },
  {
    "id": 10,
    "mode": 1,
    "levelMax": 1,
    "chapter": 1,
    "levelMin": 10,
    "ammoCount": 5,
    "tripleStar": 1,
    "doubleStar": 2,
    "singleStar": 3,
    "sceneId": 10
  },
  {
    "id": 11,
    "mode": 1,
    "levelMax": 2,
    "chapter": 1,
    "levelMin": 1,
    "ammoCount": 5,
    "tripleStar": 1,
    "doubleStar": 2,
    "singleStar": 3,
    "sceneId": 11
  },
  {
    "id": 12,
    "mode": 1,
    "levelMax": 2,
    "chapter": 1,
    "levelMin": 2,
    "ammoCount": 5,
    "tripleStar": 1,
    "doubleStar": 2,
    "singleStar": 3,
    "sceneId": 12
  },
  {
    "id": 13,
    "mode": 1,
    "levelMax": 2,
    "chapter": 1,
    "levelMin": 3,
    "ammoCount": 5,
    "tripleStar": 1,
    "doubleStar": 2,
    "singleStar": 3,
    "sceneId": 13
  },
  {
    "id": 14,
    "mode": 1,
    "levelMax": 2,
    "chapter": 1,
    "levelMin": 4,
    "ammoCount": 5,
    "tripleStar": 1,
    "doubleStar": 2,
    "singleStar": 3,
    "sceneId": 14
  },
  {
    "id": 15,
    "mode": 1,
    "levelMax": 2,
    "chapter": 1,
    "levelMin": 5,
    "ammoCount": 5,
    "tripleStar": 1,
    "doubleStar": 2,
    "singleStar": 3,
    "sceneId": 15
  },
  {
    "id": 16,
    "mode": 1,
    "levelMax": 2,
    "chapter": 1,
    "levelMin": 6,
    "ammoCount": 5,
    "tripleStar": 1,
    "doubleStar": 2,
    "singleStar": 3,
    "sceneId": 16
  },
  {
    "id": 17,
    "mode": 1,
    "levelMax": 2,
    "chapter": 1,
    "levelMin": 7,
    "ammoCount": 6,
    "tripleStar": 2,
    "doubleStar": 3,
    "singleStar": 4,
    "sceneId": 17
  },
  {
    "id": 18,
    "mode": 1,
    "levelMax": 2,
    "chapter": 1,
    "levelMin": 8,
    "ammoCount": 5,
    "tripleStar": 1,
    "doubleStar": 2,
    "singleStar": 3,
    "sceneId": 18
  },
  {
    "id": 19,
    "mode": 1,
    "levelMax": 2,
    "chapter": 1,
    "levelMin": 9,
    "ammoCount": 6,
    "tripleStar": 2,
    "doubleStar": 3,
    "singleStar": 4,
    "sceneId": 19
  },
  {
    "id": 20,
    "mode": 1,
    "levelMax": 2,
    "chapter": 1,
    "levelMin": 10,
    "ammoCount": 7,
    "tripleStar": 3,
    "doubleStar": 4,
    "singleStar": 5,
    "sceneId": 20
  },
  {
    "id": 21,
    "mode": 1,
    "levelMax": 3,
    "chapter": 1,
    "levelMin": 1,
    "ammoCount": 5,
    "tripleStar": 1,
    "doubleStar": 2,
    "singleStar": 3,
    "sceneId": 21
  },
  {
    "id": 22,
    "mode": 1,
    "levelMax": 3,
    "chapter": 1,
    "levelMin": 2,
    "ammoCount": 6,
    "tripleStar": 2,
    "doubleStar": 3,
    "singleStar": 4,
    "sceneId": 22
  },
  {
    "id": 23,
    "mode": 1,
    "levelMax": 3,
    "chapter": 1,
    "levelMin": 3,
    "ammoCount": 5,
    "tripleStar": 1,
    "doubleStar": 2,
    "singleStar": 3,
    "sceneId": 23
  },
  {
    "id": 24,
    "mode": 1,
    "levelMax": 3,
    "chapter": 1,
    "levelMin": 4,
    "ammoCount": 5,
    "tripleStar": 1,
    "doubleStar": 2,
    "singleStar": 3,
    "sceneId": 24
  },
  {
    "id": 25,
    "mode": 1,
    "levelMax": 3,
    "chapter": 1,
    "levelMin": 5,
    "ammoCount": 5,
    "tripleStar": 1,
    "doubleStar": 2,
    "singleStar": 3,
    "sceneId": 25
  },
  {
    "id": 26,
    "mode": 1,
    "levelMax": 3,
    "chapter": 1,
    "levelMin": 6,
    "ammoCount": 5,
    "tripleStar": 1,
    "doubleStar": 2,
    "singleStar": 3,
    "sceneId": 26
  },
  {
    "id": 27,
    "mode": 1,
    "levelMax": 3,
    "chapter": 1,
    "levelMin": 7,
    "ammoCount": 5,
    "tripleStar": 1,
    "doubleStar": 2,
    "singleStar": 3,
    "sceneId": 27
  },
  {
    "id": 28,
    "mode": 1,
    "levelMax": 3,
    "chapter": 1,
    "levelMin": 8,
    "ammoCount": 5,
    "tripleStar": 1,
    "doubleStar": 2,
    "singleStar": 3,
    "sceneId": 28
  },
  {
    "id": 29,
    "mode": 1,
    "levelMax": 3,
    "chapter": 1,
    "levelMin": 9,
    "ammoCount": 6,
    "tripleStar": 2,
    "doubleStar": 3,
    "singleStar": 4,
    "sceneId": 29
  },
  {
    "id": 30,
    "mode": 1,
    "levelMax": 3,
    "chapter": 1,
    "levelMin": 10,
    "ammoCount": 6,
    "tripleStar": 2,
    "doubleStar": 3,
    "singleStar": 4,
    "sceneId": 30
  },
  {
    "id": 31,
    "mode": 1,
    "levelMax": 4,
    "chapter": 1,
    "levelMin": 1,
    "ammoCount": 5,
    "tripleStar": 1,
    "doubleStar": 2,
    "singleStar": 3,
    "sceneId": 31
  },
  {
    "id": 32,
    "mode": 1,
    "levelMax": 4,
    "chapter": 1,
    "levelMin": 2,
    "ammoCount": 6,
    "tripleStar": 2,
    "doubleStar": 3,
    "singleStar": 4,
    "sceneId": 32
  },
  {
    "id": 33,
    "mode": 1,
    "levelMax": 4,
    "chapter": 1,
    "levelMin": 3,
    "ammoCount": 6,
    "tripleStar": 2,
    "doubleStar": 3,
    "singleStar": 4,
    "sceneId": 33
  },
  {
    "id": 34,
    "mode": 1,
    "levelMax": 4,
    "chapter": 1,
    "levelMin": 4,
    "ammoCount": 5,
    "tripleStar": 1,
    "doubleStar": 2,
    "singleStar": 3,
    "sceneId": 34
  },
  {
    "id": 35,
    "mode": 1,
    "levelMax": 4,
    "chapter": 1,
    "levelMin": 5,
    "ammoCount": 6,
    "tripleStar": 2,
    "doubleStar": 3,
    "singleStar": 4,
    "sceneId": 35
  },
  {
    "id": 36,
    "mode": 1,
    "levelMax": 4,
    "chapter": 1,
    "levelMin": 6,
    "ammoCount": 5,
    "tripleStar": 1,
    "doubleStar": 2,
    "singleStar": 3,
    "sceneId": 36
  },
  {
    "id": 37,
    "mode": 1,
    "levelMax": 4,
    "chapter": 1,
    "levelMin": 7,
    "ammoCount": 5,
    "tripleStar": 1,
    "doubleStar": 2,
    "singleStar": 3,
    "sceneId": 37
  },
  {
    "id": 38,
    "mode": 1,
    "levelMax": 4,
    "chapter": 1,
    "levelMin": 8,
    "ammoCount": 5,
    "tripleStar": 1,
    "doubleStar": 2,
    "singleStar": 3,
    "sceneId": 38
  },
  {
    "id": 39,
    "mode": 1,
    "levelMax": 4,
    "chapter": 1,
    "levelMin": 9,
    "ammoCount": 5,
    "tripleStar": 1,
    "doubleStar": 2,
    "singleStar": 3,
    "sceneId": 39
  },
  {
    "id": 40,
    "mode": 1,
    "levelMax": 4,
    "chapter": 1,
    "levelMin": 10,
    "ammoCount": 5,
    "tripleStar": 1,
    "doubleStar": 2,
    "singleStar": 3,
    "sceneId": 40
  },
  {
    "id": 41,
    "mode": 1,
    "levelMax": 5,
    "chapter": 1,
    "levelMin": 1,
    "ammoCount": 6,
    "tripleStar": 2,
    "doubleStar": 3,
    "singleStar": 4,
    "sceneId": 41
  },
  {
    "id": 42,
    "mode": 1,
    "levelMax": 5,
    "chapter": 1,
    "levelMin": 2,
    "ammoCount": 6,
    "tripleStar": 2,
    "doubleStar": 3,
    "singleStar": 4,
    "sceneId": 42
  },
  {
    "id": 43,
    "mode": 1,
    "levelMax": 5,
    "chapter": 1,
    "levelMin": 3,
    "ammoCount": 5,
    "tripleStar": 1,
    "doubleStar": 2,
    "singleStar": 3,
    "sceneId": 43
  },
  {
    "id": 44,
    "mode": 1,
    "levelMax": 5,
    "chapter": 1,
    "levelMin": 4,
    "ammoCount": 5,
    "tripleStar": 1,
    "doubleStar": 2,
    "singleStar": 3,
    "sceneId": 44
  },
  {
    "id": 45,
    "mode": 1,
    "levelMax": 5,
    "chapter": 1,
    "levelMin": 5,
    "ammoCount": 5,
    "tripleStar": 1,
    "doubleStar": 2,
    "singleStar": 3,
    "sceneId": 45
  },
  {
    "id": 46,
    "mode": 1,
    "levelMax": 5,
    "chapter": 1,
    "levelMin": 6,
    "ammoCount": 5,
    "tripleStar": 1,
    "doubleStar": 2,
    "singleStar": 3,
    "sceneId": 46
  },
  {
    "id": 47,
    "mode": 1,
    "levelMax": 5,
    "chapter": 1,
    "levelMin": 7,
    "ammoCount": 5,
    "tripleStar": 1,
    "doubleStar": 2,
    "singleStar": 3,
    "sceneId": 47
  },
  {
    "id": 48,
    "mode": 1,
    "levelMax": 5,
    "chapter": 1,
    "levelMin": 8,
    "ammoCount": 5,
    "tripleStar": 1,
    "doubleStar": 2,
    "singleStar": 3,
    "sceneId": 48
  },
  {
    "id": 49,
    "mode": 1,
    "levelMax": 5,
    "chapter": 1,
    "levelMin": 9,
    "ammoCount": 5,
    "tripleStar": 1,
    "doubleStar": 2,
    "singleStar": 3,
    "sceneId": 49
  },
  {
    "id": 50,
    "mode": 1,
    "levelMax": 5,
    "chapter": 1,
    "levelMin": 10,
    "ammoCount": 5,
    "tripleStar": 1,
    "doubleStar": 2,
    "singleStar": 3,
    "sceneId": 50
  },
  {
    "id": 51,
    "mode": 1,
    "levelMax": 6,
    "chapter": 1,
    "levelMin": 1,
    "ammoCount": 5,
    "tripleStar": 1,
    "doubleStar": 2,
    "singleStar": 3,
    "sceneId": 51
  },
  {
    "id": 52,
    "mode": 1,
    "levelMax": 6,
    "chapter": 1,
    "levelMin": 2,
    "ammoCount": 5,
    "tripleStar": 1,
    "doubleStar": 2,
    "singleStar": 3,
    "sceneId": 52
  },
  {
    "id": 53,
    "mode": 1,
    "levelMax": 6,
    "chapter": 1,
    "levelMin": 3,
    "ammoCount": 5,
    "tripleStar": 1,
    "doubleStar": 2,
    "singleStar": 3,
    "sceneId": 53
  },
  {
    "id": 54,
    "mode": 1,
    "levelMax": 6,
    "chapter": 1,
    "levelMin": 4,
    "ammoCount": 5,
    "tripleStar": 1,
    "doubleStar": 2,
    "singleStar": 3,
    "sceneId": 54
  },
  {
    "id": 55,
    "mode": 1,
    "levelMax": 6,
    "chapter": 1,
    "levelMin": 5,
    "ammoCount": 6,
    "tripleStar": 2,
    "doubleStar": 3,
    "singleStar": 4,
    "sceneId": 55
  },
  {
    "id": 56,
    "mode": 1,
    "levelMax": 6,
    "chapter": 1,
    "levelMin": 6,
    "ammoCount": 5,
    "tripleStar": 1,
    "doubleStar": 2,
    "singleStar": 3,
    "sceneId": 56
  },
  {
    "id": 57,
    "mode": 1,
    "levelMax": 6,
    "chapter": 1,
    "levelMin": 7,
    "ammoCount": 5,
    "tripleStar": 1,
    "doubleStar": 2,
    "singleStar": 3,
    "sceneId": 57
  },
  {
    "id": 58,
    "mode": 1,
    "levelMax": 6,
    "chapter": 1,
    "levelMin": 8,
    "ammoCount": 5,
    "tripleStar": 1,
    "doubleStar": 2,
    "singleStar": 3,
    "sceneId": 58
  },
  {
    "id": 59,
    "mode": 1,
    "levelMax": 6,
    "chapter": 1,
    "levelMin": 9,
    "ammoCount": 5,
    "tripleStar": 1,
    "doubleStar": 2,
    "singleStar": 3,
    "sceneId": 59
  },
  {
    "id": 60,
    "mode": 1,
    "levelMax": 6,
    "chapter": 1,
    "levelMin": 10,
    "ammoCount": 5,
    "tripleStar": 1,
    "doubleStar": 2,
    "singleStar": 3,
    "sceneId": 60
  },
  {
    "id": 61,
    "mode": 1,
    "levelMax": 7,
    "chapter": 2,
    "levelMin": 1,
    "ammoCount": 5,
    "tripleStar": 1,
    "doubleStar": 2,
    "singleStar": 3,
    "sceneId": 61
  },
  {
    "id": 62,
    "mode": 1,
    "levelMax": 7,
    "chapter": 2,
    "levelMin": 2,
    "ammoCount": 5,
    "tripleStar": 1,
    "doubleStar": 2,
    "singleStar": 3,
    "sceneId": 62
  },
  {
    "id": 63,
    "mode": 1,
    "levelMax": 7,
    "chapter": 2,
    "levelMin": 3,
    "ammoCount": 5,
    "tripleStar": 1,
    "doubleStar": 2,
    "singleStar": 3,
    "sceneId": 63
  },
  {
    "id": 64,
    "mode": 1,
    "levelMax": 7,
    "chapter": 2,
    "levelMin": 4,
    "ammoCount": 6,
    "tripleStar": 2,
    "doubleStar": 3,
    "singleStar": 4,
    "sceneId": 64
  },
  {
    "id": 65,
    "mode": 1,
    "levelMax": 7,
    "chapter": 2,
    "levelMin": 5,
    "ammoCount": 5,
    "tripleStar": 1,
    "doubleStar": 2,
    "singleStar": 3,
    "sceneId": 65
  },
  {
    "id": 66,
    "mode": 1,
    "levelMax": 7,
    "chapter": 2,
    "levelMin": 6,
    "ammoCount": 5,
    "tripleStar": 1,
    "doubleStar": 2,
    "singleStar": 3,
    "sceneId": 66
  },
  {
    "id": 67,
    "mode": 1,
    "levelMax": 7,
    "chapter": 2,
    "levelMin": 7,
    "ammoCount": 5,
    "tripleStar": 1,
    "doubleStar": 2,
    "singleStar": 3,
    "sceneId": 67
  },
  {
    "id": 68,
    "mode": 1,
    "levelMax": 7,
    "chapter": 2,
    "levelMin": 8,
    "ammoCount": 5,
    "tripleStar": 1,
    "doubleStar": 2,
    "singleStar": 3,
    "sceneId": 68
  },
  {
    "id": 69,
    "mode": 1,
    "levelMax": 7,
    "chapter": 2,
    "levelMin": 9,
    "ammoCount": 8,
    "tripleStar": 1,
    "doubleStar": 2,
    "singleStar": 3,
    "sceneId": 69
  },
  {
    "id": 70,
    "mode": 1,
    "levelMax": 7,
    "chapter": 2,
    "levelMin": 10,
    "ammoCount": 6,
    "tripleStar": 1,
    "doubleStar": 2,
    "singleStar": 3,
    "sceneId": 70
  },
  {
    "id": 71,
    "mode": 1,
    "levelMax": 8,
    "chapter": 2,
    "levelMin": 1,
    "ammoCount": 6,
    "tripleStar": 2,
    "doubleStar": 3,
    "singleStar": 4,
    "sceneId": 71
  },
  {
    "id": 72,
    "mode": 1,
    "levelMax": 8,
    "chapter": 2,
    "levelMin": 2,
    "ammoCount": 5,
    "tripleStar": 1,
    "doubleStar": 2,
    "singleStar": 3,
    "sceneId": 72
  },
  {
    "id": 73,
    "mode": 1,
    "levelMax": 8,
    "chapter": 2,
    "levelMin": 3,
    "ammoCount": 5,
    "tripleStar": 1,
    "doubleStar": 2,
    "singleStar": 3,
    "sceneId": 73
  },
  {
    "id": 74,
    "mode": 1,
    "levelMax": 8,
    "chapter": 2,
    "levelMin": 4,
    "ammoCount": 5,
    "tripleStar": 1,
    "doubleStar": 2,
    "singleStar": 3,
    "sceneId": 74
  },
  {
    "id": 75,
    "mode": 1,
    "levelMax": 8,
    "chapter": 2,
    "levelMin": 5,
    "ammoCount": 5,
    "tripleStar": 1,
    "doubleStar": 2,
    "singleStar": 3,
    "sceneId": 75
  },
  {
    "id": 76,
    "mode": 1,
    "levelMax": 8,
    "chapter": 2,
    "levelMin": 6,
    "ammoCount": 6,
    "tripleStar": 2,
    "doubleStar": 3,
    "singleStar": 4,
    "sceneId": 76
  },
  {
    "id": 77,
    "mode": 1,
    "levelMax": 8,
    "chapter": 2,
    "levelMin": 7,
    "ammoCount": 5,
    "tripleStar": 1,
    "doubleStar": 2,
    "singleStar": 3,
    "sceneId": 77
  },
  {
    "id": 78,
    "mode": 1,
    "levelMax": 8,
    "chapter": 2,
    "levelMin": 8,
    "ammoCount": 6,
    "tripleStar": 2,
    "doubleStar": 3,
    "singleStar": 4,
    "sceneId": 78
  },
  {
    "id": 79,
    "mode": 1,
    "levelMax": 8,
    "chapter": 2,
    "levelMin": 9,
    "ammoCount": 6,
    "tripleStar": 2,
    "doubleStar": 3,
    "singleStar": 4,
    "sceneId": 79
  },
  {
    "id": 80,
    "mode": 1,
    "levelMax": 8,
    "chapter": 2,
    "levelMin": 10,
    "ammoCount": 6,
    "tripleStar": 2,
    "doubleStar": 3,
    "singleStar": 4,
    "sceneId": 80
  },
  {
    "id": 81,
    "mode": 1,
    "levelMax": 9,
    "chapter": 2,
    "levelMin": 1,
    "ammoCount": 6,
    "tripleStar": 2,
    "doubleStar": 3,
    "singleStar": 4,
    "sceneId": 81
  },
  {
    "id": 82,
    "mode": 1,
    "levelMax": 9,
    "chapter": 2,
    "levelMin": 2,
    "ammoCount": 5,
    "tripleStar": 1,
    "doubleStar": 2,
    "singleStar": 3,
    "sceneId": 82
  },
  {
    "id": 83,
    "mode": 1,
    "levelMax": 9,
    "chapter": 2,
    "levelMin": 3,
    "ammoCount": 6,
    "tripleStar": 2,
    "doubleStar": 3,
    "singleStar": 4,
    "sceneId": 83
  },
  {
    "id": 84,
    "mode": 1,
    "levelMax": 9,
    "chapter": 2,
    "levelMin": 4,
    "ammoCount": 6,
    "tripleStar": 2,
    "doubleStar": 3,
    "singleStar": 4,
    "sceneId": 84
  },
  {
    "id": 85,
    "mode": 1,
    "levelMax": 9,
    "chapter": 2,
    "levelMin": 5,
    "ammoCount": 6,
    "tripleStar": 2,
    "doubleStar": 3,
    "singleStar": 4,
    "sceneId": 85
  },
  {
    "id": 86,
    "mode": 1,
    "levelMax": 9,
    "chapter": 2,
    "levelMin": 6,
    "ammoCount": 6,
    "tripleStar": 2,
    "doubleStar": 3,
    "singleStar": 4,
    "sceneId": 86
  },
  {
    "id": 87,
    "mode": 1,
    "levelMax": 9,
    "chapter": 2,
    "levelMin": 7,
    "ammoCount": 6,
    "tripleStar": 2,
    "doubleStar": 3,
    "singleStar": 4,
    "sceneId": 87
  },
  {
    "id": 88,
    "mode": 1,
    "levelMax": 9,
    "chapter": 2,
    "levelMin": 8,
    "ammoCount": 6,
    "tripleStar": 2,
    "doubleStar": 3,
    "singleStar": 4,
    "sceneId": 88
  },
  {
    "id": 89,
    "mode": 1,
    "levelMax": 9,
    "chapter": 1,
    "levelMin": 9,
    "ammoCount": 5,
    "tripleStar": 1,
    "doubleStar": 2,
    "singleStar": 3,
    "sceneId": 89
  },
  {
    "id": 90,
    "mode": 1,
    "levelMax": 9,
    "chapter": 1,
    "levelMin": 10,
    "ammoCount": 5,
    "tripleStar": 1,
    "doubleStar": 2,
    "singleStar": 3,
    "sceneId": 90
  },
  {
    "id": 91,
    "mode": 1,
    "levelMax": 10,
    "chapter": 2,
    "levelMin": 1,
    "ammoCount": 5,
    "tripleStar": 1,
    "doubleStar": 2,
    "singleStar": 3,
    "sceneId": 91
  },
  {
    "id": 92,
    "mode": 1,
    "levelMax": 10,
    "chapter": 2,
    "levelMin": 2,
    "ammoCount": 5,
    "tripleStar": 1,
    "doubleStar": 2,
    "singleStar": 3,
    "sceneId": 92
  },
  {
    "id": 93,
    "mode": 1,
    "levelMax": 10,
    "chapter": 2,
    "levelMin": 3,
    "ammoCount": 5,
    "tripleStar": 1,
    "doubleStar": 2,
    "singleStar": 3,
    "sceneId": 93
  },
  {
    "id": 94,
    "mode": 1,
    "levelMax": 10,
    "chapter": 2,
    "levelMin": 4,
    "ammoCount": 5,
    "tripleStar": 1,
    "doubleStar": 2,
    "singleStar": 3,
    "sceneId": 94
  },
  {
    "id": 95,
    "mode": 1,
    "levelMax": 10,
    "chapter": 2,
    "levelMin": 5,
    "ammoCount": 5,
    "tripleStar": 1,
    "doubleStar": 2,
    "singleStar": 3,
    "sceneId": 95
  },
  {
    "id": 96,
    "mode": 1,
    "levelMax": 10,
    "chapter": 2,
    "levelMin": 6,
    "ammoCount": 6,
    "tripleStar": 2,
    "doubleStar": 3,
    "singleStar": 4,
    "sceneId": 96
  },
  {
    "id": 97,
    "mode": 1,
    "levelMax": 10,
    "chapter": 2,
    "levelMin": 7,
    "ammoCount": 6,
    "tripleStar": 2,
    "doubleStar": 3,
    "singleStar": 4,
    "sceneId": 97
  },
  {
    "id": 98,
    "mode": 1,
    "levelMax": 10,
    "chapter": 2,
    "levelMin": 8,
    "ammoCount": 5,
    "tripleStar": 1,
    "doubleStar": 2,
    "singleStar": 3,
    "sceneId": 98
  },
  {
    "id": 99,
    "mode": 1,
    "levelMax": 10,
    "chapter": 2,
    "levelMin": 9,
    "ammoCount": 5,
    "tripleStar": 1,
    "doubleStar": 2,
    "singleStar": 3,
    "sceneId": 99
  },
  {
    "id": 100,
    "mode": 1,
    "levelMax": 10,
    "chapter": 2,
    "levelMin": 10,
    "ammoCount": 8,
    "tripleStar": 5,
    "doubleStar": 6,
    "singleStar": 7,
    "sceneId": 100
  },
  {
    "id": 101,
    "mode": 1,
    "levelMax": 11,
    "chapter": 2,
    "levelMin": 1,
    "ammoCount": 5,
    "tripleStar": 1,
    "doubleStar": 2,
    "singleStar": 3,
    "sceneId": 101
  },
  {
    "id": 102,
    "mode": 1,
    "levelMax": 11,
    "chapter": 2,
    "levelMin": 2,
    "ammoCount": 5,
    "tripleStar": 1,
    "doubleStar": 2,
    "singleStar": 3,
    "sceneId": 102
  },
  {
    "id": 103,
    "mode": 1,
    "levelMax": 11,
    "chapter": 2,
    "levelMin": 3,
    "ammoCount": 5,
    "tripleStar": 1,
    "doubleStar": 2,
    "singleStar": 3,
    "sceneId": 103
  },
  {
    "id": 104,
    "mode": 1,
    "levelMax": 11,
    "chapter": 2,
    "levelMin": 4,
    "ammoCount": 6,
    "tripleStar": 2,
    "doubleStar": 3,
    "singleStar": 4,
    "sceneId": 104
  },
  {
    "id": 105,
    "mode": 1,
    "levelMax": 11,
    "chapter": 2,
    "levelMin": 5,
    "ammoCount": 5,
    "tripleStar": 1,
    "doubleStar": 2,
    "singleStar": 3,
    "sceneId": 105
  },
  {
    "id": 106,
    "mode": 1,
    "levelMax": 11,
    "chapter": 2,
    "levelMin": 6,
    "ammoCount": 5,
    "tripleStar": 1,
    "doubleStar": 2,
    "singleStar": 3,
    "sceneId": 106
  },
  {
    "id": 107,
    "mode": 1,
    "levelMax": 11,
    "chapter": 2,
    "levelMin": 7,
    "ammoCount": 5,
    "tripleStar": 1,
    "doubleStar": 2,
    "singleStar": 3,
    "sceneId": 107
  },
  {
    "id": 108,
    "mode": 1,
    "levelMax": 11,
    "chapter": 2,
    "levelMin": 8,
    "ammoCount": 5,
    "tripleStar": 1,
    "doubleStar": 2,
    "singleStar": 3,
    "sceneId": 108
  },
  {
    "id": 109,
    "mode": 1,
    "levelMax": 11,
    "chapter": 2,
    "levelMin": 9,
    "ammoCount": 5,
    "tripleStar": 1,
    "doubleStar": 2,
    "singleStar": 3,
    "sceneId": 109
  },
  {
    "id": 110,
    "mode": 1,
    "levelMax": 11,
    "chapter": 2,
    "levelMin": 10,
    "ammoCount": 5,
    "tripleStar": 1,
    "doubleStar": 2,
    "singleStar": 3,
    "sceneId": 110
  },
  {
    "id": 111,
    "mode": 1,
    "levelMax": 12,
    "chapter": 2,
    "levelMin": 1,
    "ammoCount": 5,
    "tripleStar": 1,
    "doubleStar": 2,
    "singleStar": 3,
    "sceneId": 111
  },
  {
    "id": 112,
    "mode": 1,
    "levelMax": 12,
    "chapter": 2,
    "levelMin": 2,
    "ammoCount": 5,
    "tripleStar": 1,
    "doubleStar": 2,
    "singleStar": 3,
    "sceneId": 112
  },
  {
    "id": 113,
    "mode": 1,
    "levelMax": 12,
    "chapter": 2,
    "levelMin": 3,
    "ammoCount": 5,
    "tripleStar": 1,
    "doubleStar": 2,
    "singleStar": 3,
    "sceneId": 113
  },
  {
    "id": 114,
    "mode": 1,
    "levelMax": 12,
    "chapter": 2,
    "levelMin": 4,
    "ammoCount": 5,
    "tripleStar": 1,
    "doubleStar": 2,
    "singleStar": 3,
    "sceneId": 114
  },
  {
    "id": 115,
    "mode": 1,
    "levelMax": 12,
    "chapter": 2,
    "levelMin": 5,
    "ammoCount": 6,
    "tripleStar": 2,
    "doubleStar": 3,
    "singleStar": 4,
    "sceneId": 115
  },
  {
    "id": 116,
    "mode": 1,
    "levelMax": 12,
    "chapter": 2,
    "levelMin": 6,
    "ammoCount": 5,
    "tripleStar": 1,
    "doubleStar": 2,
    "singleStar": 3,
    "sceneId": 116
  },
  {
    "id": 117,
    "mode": 1,
    "levelMax": 12,
    "chapter": 2,
    "levelMin": 7,
    "ammoCount": 5,
    "tripleStar": 1,
    "doubleStar": 2,
    "singleStar": 3,
    "sceneId": 117
  },
  {
    "id": 118,
    "mode": 1,
    "levelMax": 12,
    "chapter": 2,
    "levelMin": 8,
    "ammoCount": 5,
    "tripleStar": 1,
    "doubleStar": 2,
    "singleStar": 3,
    "sceneId": 118
  },
  {
    "id": 119,
    "mode": 1,
    "levelMax": 12,
    "chapter": 2,
    "levelMin": 9,
    "ammoCount": 5,
    "tripleStar": 1,
    "doubleStar": 2,
    "singleStar": 3,
    "sceneId": 119
  },
  {
    "id": 120,
    "mode": 1,
    "levelMax": 12,
    "chapter": 2,
    "levelMin": 10,
    "ammoCount": 6,
    "tripleStar": 2,
    "doubleStar": 3,
    "singleStar": 4,
    "sceneId": 120
  },
  {
    "id": 121,
    "mode": 1,
    "levelMax": 13,
    "chapter": 3,
    "levelMin": 1,
    "ammoCount": 5,
    "tripleStar": 1,
    "doubleStar": 2,
    "singleStar": 3,
    "sceneId": 121
  },
  {
    "id": 122,
    "mode": 1,
    "levelMax": 13,
    "chapter": 3,
    "levelMin": 2,
    "ammoCount": 5,
    "tripleStar": 1,
    "doubleStar": 2,
    "singleStar": 3,
    "sceneId": 122
  },
  {
    "id": 123,
    "mode": 1,
    "levelMax": 13,
    "chapter": 3,
    "levelMin": 3,
    "ammoCount": 5,
    "tripleStar": 1,
    "doubleStar": 2,
    "singleStar": 3,
    "sceneId": 123
  },
  {
    "id": 124,
    "mode": 1,
    "levelMax": 13,
    "chapter": 3,
    "levelMin": 4,
    "ammoCount": 6,
    "tripleStar": 2,
    "doubleStar": 3,
    "singleStar": 4,
    "sceneId": 124
  },
  {
    "id": 125,
    "mode": 1,
    "levelMax": 13,
    "chapter": 3,
    "levelMin": 5,
    "ammoCount": 5,
    "tripleStar": 1,
    "doubleStar": 2,
    "singleStar": 3,
    "sceneId": 125
  },
  {
    "id": 126,
    "mode": 1,
    "levelMax": 13,
    "chapter": 3,
    "levelMin": 6,
    "ammoCount": 5,
    "tripleStar": 1,
    "doubleStar": 2,
    "singleStar": 3,
    "sceneId": 126
  },
  {
    "id": 127,
    "mode": 1,
    "levelMax": 13,
    "chapter": 3,
    "levelMin": 7,
    "ammoCount": 5,
    "tripleStar": 1,
    "doubleStar": 2,
    "singleStar": 3,
    "sceneId": 127
  },
  {
    "id": 128,
    "mode": 1,
    "levelMax": 13,
    "chapter": 3,
    "levelMin": 8,
    "ammoCount": 5,
    "tripleStar": 1,
    "doubleStar": 2,
    "singleStar": 3,
    "sceneId": 128
  },
  {
    "id": 129,
    "mode": 1,
    "levelMax": 13,
    "chapter": 3,
    "levelMin": 9,
    "ammoCount": 5,
    "tripleStar": 1,
    "doubleStar": 2,
    "singleStar": 3,
    "sceneId": 129
  },
  {
    "id": 130,
    "mode": 1,
    "levelMax": 13,
    "chapter": 3,
    "levelMin": 10,
    "ammoCount": 5,
    "tripleStar": 1,
    "doubleStar": 2,
    "singleStar": 3,
    "sceneId": 130
  },
  {
    "id": 131,
    "mode": 1,
    "levelMax": 14,
    "chapter": 3,
    "levelMin": 1,
    "ammoCount": 5,
    "tripleStar": 1,
    "doubleStar": 2,
    "singleStar": 3,
    "sceneId": 131
  },
  {
    "id": 132,
    "mode": 1,
    "levelMax": 14,
    "chapter": 3,
    "levelMin": 2,
    "ammoCount": 5,
    "tripleStar": 1,
    "doubleStar": 2,
    "singleStar": 3,
    "sceneId": 132
  },
  {
    "id": 133,
    "mode": 1,
    "levelMax": 14,
    "chapter": 3,
    "levelMin": 3,
    "ammoCount": 6,
    "tripleStar": 2,
    "doubleStar": 3,
    "singleStar": 4,
    "sceneId": 133
  },
  {
    "id": 134,
    "mode": 1,
    "levelMax": 14,
    "chapter": 3,
    "levelMin": 4,
    "ammoCount": 5,
    "tripleStar": 1,
    "doubleStar": 2,
    "singleStar": 3,
    "sceneId": 134
  },
  {
    "id": 135,
    "mode": 1,
    "levelMax": 14,
    "chapter": 3,
    "levelMin": 5,
    "ammoCount": 5,
    "tripleStar": 1,
    "doubleStar": 2,
    "singleStar": 3,
    "sceneId": 135
  },
  {
    "id": 136,
    "mode": 1,
    "levelMax": 14,
    "chapter": 3,
    "levelMin": 6,
    "ammoCount": 5,
    "tripleStar": 1,
    "doubleStar": 2,
    "singleStar": 3,
    "sceneId": 136
  },
  {
    "id": 137,
    "mode": 1,
    "levelMax": 14,
    "chapter": 3,
    "levelMin": 7,
    "ammoCount": 5,
    "tripleStar": 1,
    "doubleStar": 2,
    "singleStar": 3,
    "sceneId": 137
  },
  {
    "id": 138,
    "mode": 1,
    "levelMax": 14,
    "chapter": 3,
    "levelMin": 8,
    "ammoCount": 5,
    "tripleStar": 1,
    "doubleStar": 2,
    "singleStar": 3,
    "sceneId": 138
  },
  {
    "id": 139,
    "mode": 1,
    "levelMax": 14,
    "chapter": 3,
    "levelMin": 9,
    "ammoCount": 5,
    "tripleStar": 1,
    "doubleStar": 2,
    "singleStar": 3,
    "sceneId": 139
  },
  {
    "id": 140,
    "mode": 1,
    "levelMax": 14,
    "chapter": 3,
    "levelMin": 10,
    "ammoCount": 5,
    "tripleStar": 1,
    "doubleStar": 2,
    "singleStar": 3,
    "sceneId": 140
  },
  {
    "id": 141,
    "mode": 1,
    "levelMax": 15,
    "chapter": 3,
    "levelMin": 1,
    "ammoCount": 5,
    "tripleStar": 1,
    "doubleStar": 2,
    "singleStar": 3,
    "sceneId": 141
  },
  {
    "id": 142,
    "mode": 1,
    "levelMax": 15,
    "chapter": 3,
    "levelMin": 2,
    "ammoCount": 5,
    "tripleStar": 1,
    "doubleStar": 2,
    "singleStar": 3,
    "sceneId": 142
  },
  {
    "id": 143,
    "mode": 1,
    "levelMax": 15,
    "chapter": 3,
    "levelMin": 3,
    "ammoCount": 5,
    "tripleStar": 1,
    "doubleStar": 2,
    "singleStar": 3,
    "sceneId": 143
  },
  {
    "id": 144,
    "mode": 1,
    "levelMax": 15,
    "chapter": 3,
    "levelMin": 4,
    "ammoCount": 5,
    "tripleStar": 1,
    "doubleStar": 2,
    "singleStar": 3,
    "sceneId": 144
  },
  {
    "id": 145,
    "mode": 1,
    "levelMax": 15,
    "chapter": 3,
    "levelMin": 5,
    "ammoCount": 5,
    "tripleStar": 1,
    "doubleStar": 2,
    "singleStar": 3,
    "sceneId": 145
  },
  {
    "id": 146,
    "mode": 1,
    "levelMax": 15,
    "chapter": 3,
    "levelMin": 6,
    "ammoCount": 5,
    "tripleStar": 1,
    "doubleStar": 2,
    "singleStar": 3,
    "sceneId": 146
  },
  {
    "id": 147,
    "mode": 1,
    "levelMax": 15,
    "chapter": 3,
    "levelMin": 7,
    "ammoCount": 5,
    "tripleStar": 1,
    "doubleStar": 2,
    "singleStar": 3,
    "sceneId": 147
  },
  {
    "id": 148,
    "mode": 1,
    "levelMax": 15,
    "chapter": 3,
    "levelMin": 8,
    "ammoCount": 5,
    "tripleStar": 1,
    "doubleStar": 2,
    "singleStar": 3,
    "sceneId": 148
  },
  {
    "id": 149,
    "mode": 1,
    "levelMax": 15,
    "chapter": 3,
    "levelMin": 9,
    "ammoCount": 5,
    "tripleStar": 1,
    "doubleStar": 2,
    "singleStar": 3,
    "sceneId": 149
  },
  {
    "id": 150,
    "mode": 1,
    "levelMax": 15,
    "chapter": 3,
    "levelMin": 10,
    "ammoCount": 5,
    "tripleStar": 1,
    "doubleStar": 2,
    "singleStar": 3,
    "sceneId": 150
  },
  {
    "id": 151,
    "mode": 1,
    "levelMax": 16,
    "chapter": 3,
    "levelMin": 1,
    "ammoCount": 5,
    "tripleStar": 1,
    "doubleStar": 2,
    "singleStar": 3,
    "sceneId": 151
  },
  {
    "id": 152,
    "mode": 1,
    "levelMax": 16,
    "chapter": 3,
    "levelMin": 2,
    "ammoCount": 5,
    "tripleStar": 1,
    "doubleStar": 2,
    "singleStar": 3,
    "sceneId": 152
  },
  {
    "id": 153,
    "mode": 1,
    "levelMax": 16,
    "chapter": 3,
    "levelMin": 3,
    "ammoCount": 5,
    "tripleStar": 1,
    "doubleStar": 2,
    "singleStar": 3,
    "sceneId": 153
  },
  {
    "id": 154,
    "mode": 1,
    "levelMax": 16,
    "chapter": 3,
    "levelMin": 4,
    "ammoCount": 5,
    "tripleStar": 1,
    "doubleStar": 2,
    "singleStar": 3,
    "sceneId": 154
  },
  {
    "id": 155,
    "mode": 1,
    "levelMax": 16,
    "chapter": 3,
    "levelMin": 5,
    "ammoCount": 5,
    "tripleStar": 1,
    "doubleStar": 2,
    "singleStar": 3,
    "sceneId": 155
  },
  {
    "id": 156,
    "mode": 1,
    "levelMax": 16,
    "chapter": 3,
    "levelMin": 6,
    "ammoCount": 5,
    "tripleStar": 1,
    "doubleStar": 2,
    "singleStar": 3,
    "sceneId": 156
  },
  {
    "id": 157,
    "mode": 1,
    "levelMax": 16,
    "chapter": 3,
    "levelMin": 7,
    "ammoCount": 5,
    "tripleStar": 1,
    "doubleStar": 2,
    "singleStar": 3,
    "sceneId": 157
  },
  {
    "id": 158,
    "mode": 1,
    "levelMax": 16,
    "chapter": 3,
    "levelMin": 8,
    "ammoCount": 6,
    "tripleStar": 2,
    "doubleStar": 3,
    "singleStar": 4,
    "sceneId": 158
  },
  {
    "id": 159,
    "mode": 1,
    "levelMax": 16,
    "chapter": 3,
    "levelMin": 9,
    "ammoCount": 5,
    "tripleStar": 1,
    "doubleStar": 2,
    "singleStar": 3,
    "sceneId": 159
  },
  {
    "id": 160,
    "mode": 1,
    "levelMax": 16,
    "chapter": 3,
    "levelMin": 10,
    "ammoCount": 5,
    "tripleStar": 1,
    "doubleStar": 2,
    "singleStar": 3,
    "sceneId": 160
  },
  {
    "id": 161,
    "mode": 1,
    "levelMax": 17,
    "chapter": 3,
    "levelMin": 1,
    "ammoCount": 5,
    "tripleStar": 1,
    "doubleStar": 2,
    "singleStar": 3,
    "sceneId": 161
  },
  {
    "id": 162,
    "mode": 1,
    "levelMax": 17,
    "chapter": 3,
    "levelMin": 2,
    "ammoCount": 5,
    "tripleStar": 1,
    "doubleStar": 2,
    "singleStar": 3,
    "sceneId": 162
  },
  {
    "id": 163,
    "mode": 1,
    "levelMax": 17,
    "chapter": 3,
    "levelMin": 3,
    "ammoCount": 6,
    "tripleStar": 2,
    "doubleStar": 3,
    "singleStar": 4,
    "sceneId": 163
  },
  {
    "id": 164,
    "mode": 1,
    "levelMax": 17,
    "chapter": 3,
    "levelMin": 4,
    "ammoCount": 5,
    "tripleStar": 1,
    "doubleStar": 2,
    "singleStar": 3,
    "sceneId": 164
  },
  {
    "id": 165,
    "mode": 1,
    "levelMax": 17,
    "chapter": 3,
    "levelMin": 5,
    "ammoCount": 5,
    "tripleStar": 1,
    "doubleStar": 2,
    "singleStar": 3,
    "sceneId": 165
  },
  {
    "id": 166,
    "mode": 1,
    "levelMax": 17,
    "chapter": 3,
    "levelMin": 6,
    "ammoCount": 5,
    "tripleStar": 1,
    "doubleStar": 2,
    "singleStar": 3,
    "sceneId": 166
  },
  {
    "id": 167,
    "mode": 1,
    "levelMax": 17,
    "chapter": 3,
    "levelMin": 7,
    "ammoCount": 5,
    "tripleStar": 1,
    "doubleStar": 2,
    "singleStar": 3,
    "sceneId": 167
  },
  {
    "id": 168,
    "mode": 1,
    "levelMax": 17,
    "chapter": 3,
    "levelMin": 8,
    "ammoCount": 5,
    "tripleStar": 1,
    "doubleStar": 2,
    "singleStar": 3,
    "sceneId": 168
  },
  {
    "id": 169,
    "mode": 1,
    "levelMax": 17,
    "chapter": 3,
    "levelMin": 9,
    "ammoCount": 6,
    "tripleStar": 2,
    "doubleStar": 3,
    "singleStar": 4,
    "sceneId": 169
  },
  {
    "id": 170,
    "mode": 1,
    "levelMax": 17,
    "chapter": 3,
    "levelMin": 10,
    "ammoCount": 6,
    "tripleStar": 2,
    "doubleStar": 3,
    "singleStar": 4,
    "sceneId": 170
  },
  {
    "id": 171,
    "mode": 1,
    "levelMax": 18,
    "chapter": 3,
    "levelMin": 1,
    "ammoCount": 5,
    "tripleStar": 1,
    "doubleStar": 2,
    "singleStar": 3,
    "sceneId": 171
  },
  {
    "id": 172,
    "mode": 1,
    "levelMax": 18,
    "chapter": 3,
    "levelMin": 2,
    "ammoCount": 6,
    "tripleStar": 2,
    "doubleStar": 3,
    "singleStar": 4,
    "sceneId": 172
  },
  {
    "id": 173,
    "mode": 1,
    "levelMax": 18,
    "chapter": 3,
    "levelMin": 3,
    "ammoCount": 5,
    "tripleStar": 1,
    "doubleStar": 2,
    "singleStar": 3,
    "sceneId": 173
  },
  {
    "id": 174,
    "mode": 1,
    "levelMax": 18,
    "chapter": 3,
    "levelMin": 4,
    "ammoCount": 6,
    "tripleStar": 2,
    "doubleStar": 3,
    "singleStar": 4,
    "sceneId": 174
  },
  {
    "id": 175,
    "mode": 1,
    "levelMax": 18,
    "chapter": 3,
    "levelMin": 5,
    "ammoCount": 5,
    "tripleStar": 1,
    "doubleStar": 2,
    "singleStar": 3,
    "sceneId": 175
  },
  {
    "id": 176,
    "mode": 1,
    "levelMax": 18,
    "chapter": 3,
    "levelMin": 6,
    "ammoCount": 5,
    "tripleStar": 1,
    "doubleStar": 2,
    "singleStar": 3,
    "sceneId": 176
  },
  {
    "id": 177,
    "mode": 1,
    "levelMax": 18,
    "chapter": 3,
    "levelMin": 7,
    "ammoCount": 6,
    "tripleStar": 2,
    "doubleStar": 3,
    "singleStar": 4,
    "sceneId": 177
  },
  {
    "id": 178,
    "mode": 1,
    "levelMax": 18,
    "chapter": 3,
    "levelMin": 8,
    "ammoCount": 6,
    "tripleStar": 2,
    "doubleStar": 3,
    "singleStar": 4,
    "sceneId": 178
  },
  {
    "id": 179,
    "mode": 1,
    "levelMax": 18,
    "chapter": 3,
    "levelMin": 9,
    "ammoCount": 6,
    "tripleStar": 2,
    "doubleStar": 3,
    "singleStar": 4,
    "sceneId": 179
  },
  {
    "id": 180,
    "mode": 1,
    "levelMax": 18,
    "chapter": 3,
    "levelMin": 10,
    "ammoCount": 6,
    "tripleStar": 2,
    "doubleStar": 3,
    "singleStar": 4,
    "sceneId": 180
  },
  {
    "id": 181,
    "mode": 1,
    "levelMax": 19,
    "chapter": 4,
    "levelMin": 1,
    "ammoCount": 5,
    "tripleStar": 1,
    "doubleStar": 2,
    "singleStar": 3,
    "sceneId": 181
  },
  {
    "id": 182,
    "mode": 1,
    "levelMax": 19,
    "chapter": 4,
    "levelMin": 2,
    "ammoCount": 5,
    "tripleStar": 2,
    "doubleStar": 3,
    "singleStar": 4,
    "sceneId": 182
  },
  {
    "id": 183,
    "mode": 1,
    "levelMax": 19,
    "chapter": 4,
    "levelMin": 3,
    "ammoCount": 5,
    "tripleStar": 1,
    "doubleStar": 2,
    "singleStar": 3,
    "sceneId": 183
  },
  {
    "id": 184,
    "mode": 1,
    "levelMax": 19,
    "chapter": 4,
    "levelMin": 4,
    "ammoCount": 5,
    "tripleStar": 1,
    "doubleStar": 2,
    "singleStar": 3,
    "sceneId": 184
  },
  {
    "id": 185,
    "mode": 1,
    "levelMax": 19,
    "chapter": 4,
    "levelMin": 5,
    "ammoCount": 5,
    "tripleStar": 2,
    "doubleStar": 3,
    "singleStar": 4,
    "sceneId": 185
  },
  {
    "id": 186,
    "mode": 1,
    "levelMax": 19,
    "chapter": 4,
    "levelMin": 6,
    "ammoCount": 5,
    "tripleStar": 1,
    "doubleStar": 2,
    "singleStar": 3,
    "sceneId": 186
  },
  {
    "id": 187,
    "mode": 1,
    "levelMax": 19,
    "chapter": 4,
    "levelMin": 7,
    "ammoCount": 5,
    "tripleStar": 1,
    "doubleStar": 2,
    "singleStar": 3,
    "sceneId": 187
  },
  {
    "id": 188,
    "mode": 1,
    "levelMax": 19,
    "chapter": 4,
    "levelMin": 8,
    "ammoCount": 5,
    "tripleStar": 1,
    "doubleStar": 2,
    "singleStar": 3,
    "sceneId": 188
  },
  {
    "id": 189,
    "mode": 1,
    "levelMax": 19,
    "chapter": 4,
    "levelMin": 9,
    "ammoCount": 5,
    "tripleStar": 1,
    "doubleStar": 2,
    "singleStar": 3,
    "sceneId": 189
  },
  {
    "id": 190,
    "mode": 1,
    "levelMax": 19,
    "chapter": 4,
    "levelMin": 10,
    "ammoCount": 5,
    "tripleStar": 1,
    "doubleStar": 2,
    "singleStar": 3,
    "sceneId": 190
  },
  {
    "id": 191,
    "mode": 1,
    "levelMax": 20,
    "chapter": 4,
    "levelMin": 1,
    "ammoCount": 5,
    "tripleStar": 1,
    "doubleStar": 2,
    "singleStar": 3,
    "sceneId": 191
  },
  {
    "id": 192,
    "mode": 1,
    "levelMax": 20,
    "chapter": 4,
    "levelMin": 2,
    "ammoCount": 5,
    "tripleStar": 2,
    "doubleStar": 3,
    "singleStar": 4,
    "sceneId": 192
  },
  {
    "id": 193,
    "mode": 1,
    "levelMax": 20,
    "chapter": 4,
    "levelMin": 3,
    "ammoCount": 5,
    "tripleStar": 1,
    "doubleStar": 2,
    "singleStar": 3,
    "sceneId": 193
  },
  {
    "id": 194,
    "mode": 1,
    "levelMax": 20,
    "chapter": 4,
    "levelMin": 4,
    "ammoCount": 5,
    "tripleStar": 1,
    "doubleStar": 2,
    "singleStar": 3,
    "sceneId": 194
  },
  {
    "id": 195,
    "mode": 1,
    "levelMax": 20,
    "chapter": 4,
    "levelMin": 5,
    "ammoCount": 5,
    "tripleStar": 1,
    "doubleStar": 2,
    "singleStar": 3,
    "sceneId": 195
  },
  {
    "id": 196,
    "mode": 1,
    "levelMax": 20,
    "chapter": 4,
    "levelMin": 6,
    "ammoCount": 5,
    "tripleStar": 1,
    "doubleStar": 2,
    "singleStar": 3,
    "sceneId": 196
  },
  {
    "id": 197,
    "mode": 1,
    "levelMax": 20,
    "chapter": 4,
    "levelMin": 7,
    "ammoCount": 5,
    "tripleStar": 1,
    "doubleStar": 2,
    "singleStar": 3,
    "sceneId": 197
  },
  {
    "id": 198,
    "mode": 1,
    "levelMax": 20,
    "chapter": 4,
    "levelMin": 8,
    "ammoCount": 5,
    "tripleStar": 1,
    "doubleStar": 2,
    "singleStar": 3,
    "sceneId": 198
  },
  {
    "id": 199,
    "mode": 1,
    "levelMax": 20,
    "chapter": 4,
    "levelMin": 9,
    "ammoCount": 5,
    "tripleStar": 1,
    "doubleStar": 2,
    "singleStar": 3,
    "sceneId": 199
  },
  {
    "id": 200,
    "mode": 1,
    "levelMax": 20,
    "chapter": 4,
    "levelMin": 10,
    "ammoCount": 5,
    "tripleStar": 1,
    "doubleStar": 2,
    "singleStar": 3,
    "sceneId": 200
  },
  {
    "id": 201,
    "mode": 1,
    "levelMax": 21,
    "chapter": 4,
    "levelMin": 1,
    "ammoCount": 5,
    "tripleStar": 1,
    "doubleStar": 2,
    "singleStar": 3,
    "sceneId": 201
  },
  {
    "id": 202,
    "mode": 1,
    "levelMax": 21,
    "chapter": 4,
    "levelMin": 2,
    "ammoCount": 5,
    "tripleStar": 1,
    "doubleStar": 2,
    "singleStar": 3,
    "sceneId": 202
  },
  {
    "id": 203,
    "mode": 1,
    "levelMax": 21,
    "chapter": 4,
    "levelMin": 3,
    "ammoCount": 5,
    "tripleStar": 1,
    "doubleStar": 2,
    "singleStar": 3,
    "sceneId": 203
  },
  {
    "id": 204,
    "mode": 1,
    "levelMax": 21,
    "chapter": 4,
    "levelMin": 4,
    "ammoCount": 5,
    "tripleStar": 2,
    "doubleStar": 3,
    "singleStar": 4,
    "sceneId": 204
  },
  {
    "id": 205,
    "mode": 1,
    "levelMax": 21,
    "chapter": 4,
    "levelMin": 5,
    "ammoCount": 5,
    "tripleStar": 2,
    "doubleStar": 3,
    "singleStar": 4,
    "sceneId": 205
  },
  {
    "id": 206,
    "mode": 1,
    "levelMax": 21,
    "chapter": 4,
    "levelMin": 6,
    "ammoCount": 5,
    "tripleStar": 1,
    "doubleStar": 2,
    "singleStar": 3,
    "sceneId": 206
  },
  {
    "id": 207,
    "mode": 1,
    "levelMax": 21,
    "chapter": 4,
    "levelMin": 7,
    "ammoCount": 5,
    "tripleStar": 1,
    "doubleStar": 2,
    "singleStar": 3,
    "sceneId": 207
  },
  {
    "id": 208,
    "mode": 1,
    "levelMax": 21,
    "chapter": 4,
    "levelMin": 8,
    "ammoCount": 5,
    "tripleStar": 1,
    "doubleStar": 2,
    "singleStar": 3,
    "sceneId": 208
  },
  {
    "id": 209,
    "mode": 1,
    "levelMax": 21,
    "chapter": 4,
    "levelMin": 9,
    "ammoCount": 5,
    "tripleStar": 1,
    "doubleStar": 2,
    "singleStar": 3,
    "sceneId": 209
  },
  {
    "id": 210,
    "mode": 1,
    "levelMax": 21,
    "chapter": 4,
    "levelMin": 10,
    "ammoCount": 5,
    "tripleStar": 1,
    "doubleStar": 2,
    "singleStar": 3,
    "sceneId": 210
  },
  {
    "id": 211,
    "mode": 1,
    "levelMax": 22,
    "chapter": 4,
    "levelMin": 1,
    "ammoCount": 5,
    "tripleStar": 1,
    "doubleStar": 2,
    "singleStar": 3,
    "sceneId": 211
  },
  {
    "id": 212,
    "mode": 1,
    "levelMax": 22,
    "chapter": 4,
    "levelMin": 2,
    "ammoCount": 5,
    "tripleStar": 2,
    "doubleStar": 3,
    "singleStar": 4,
    "sceneId": 212
  },
  {
    "id": 213,
    "mode": 1,
    "levelMax": 22,
    "chapter": 4,
    "levelMin": 3,
    "ammoCount": 5,
    "tripleStar": 1,
    "doubleStar": 2,
    "singleStar": 3,
    "sceneId": 213
  },
  {
    "id": 214,
    "mode": 1,
    "levelMax": 22,
    "chapter": 4,
    "levelMin": 4,
    "ammoCount": 5,
    "tripleStar": 1,
    "doubleStar": 2,
    "singleStar": 3,
    "sceneId": 214
  },
  {
    "id": 215,
    "mode": 1,
    "levelMax": 22,
    "chapter": 4,
    "levelMin": 5,
    "ammoCount": 5,
    "tripleStar": 1,
    "doubleStar": 2,
    "singleStar": 3,
    "sceneId": 215
  },
  {
    "id": 216,
    "mode": 1,
    "levelMax": 22,
    "chapter": 4,
    "levelMin": 6,
    "ammoCount": 5,
    "tripleStar": 1,
    "doubleStar": 2,
    "singleStar": 3,
    "sceneId": 216
  },
  {
    "id": 217,
    "mode": 1,
    "levelMax": 22,
    "chapter": 4,
    "levelMin": 7,
    "ammoCount": 5,
    "tripleStar": 1,
    "doubleStar": 2,
    "singleStar": 3,
    "sceneId": 217
  },
  {
    "id": 218,
    "mode": 1,
    "levelMax": 22,
    "chapter": 4,
    "levelMin": 8,
    "ammoCount": 5,
    "tripleStar": 1,
    "doubleStar": 2,
    "singleStar": 3,
    "sceneId": 218
  },
  {
    "id": 219,
    "mode": 1,
    "levelMax": 22,
    "chapter": 4,
    "levelMin": 9,
    "ammoCount": 5,
    "tripleStar": 1,
    "doubleStar": 2,
    "singleStar": 3,
    "sceneId": 219
  },
  {
    "id": 220,
    "mode": 1,
    "levelMax": 22,
    "chapter": 4,
    "levelMin": 10,
    "ammoCount": 5,
    "tripleStar": 1,
    "doubleStar": 2,
    "singleStar": 3,
    "sceneId": 220
  },
  {
    "id": 221,
    "mode": 1,
    "levelMax": 23,
    "chapter": 4,
    "levelMin": 1,
    "ammoCount": 5,
    "tripleStar": 1,
    "doubleStar": 2,
    "singleStar": 3,
    "sceneId": 221
  },
  {
    "id": 222,
    "mode": 1,
    "levelMax": 23,
    "chapter": 4,
    "levelMin": 2,
    "ammoCount": 5,
    "tripleStar": 1,
    "doubleStar": 2,
    "singleStar": 3,
    "sceneId": 222
  },
  {
    "id": 223,
    "mode": 1,
    "levelMax": 23,
    "chapter": 4,
    "levelMin": 3,
    "ammoCount": 5,
    "tripleStar": 1,
    "doubleStar": 2,
    "singleStar": 3,
    "sceneId": 223
  },
  {
    "id": 224,
    "mode": 1,
    "levelMax": 23,
    "chapter": 4,
    "levelMin": 4,
    "ammoCount": 5,
    "tripleStar": 1,
    "doubleStar": 2,
    "singleStar": 3,
    "sceneId": 224
  },
  {
    "id": 225,
    "mode": 1,
    "levelMax": 23,
    "chapter": 4,
    "levelMin": 5,
    "ammoCount": 5,
    "tripleStar": 1,
    "doubleStar": 2,
    "singleStar": 3,
    "sceneId": 225
  },
  {
    "id": 226,
    "mode": 1,
    "levelMax": 23,
    "chapter": 4,
    "levelMin": 6,
    "ammoCount": 5,
    "tripleStar": 1,
    "doubleStar": 2,
    "singleStar": 3,
    "sceneId": 226
  },
  {
    "id": 227,
    "mode": 1,
    "levelMax": 23,
    "chapter": 4,
    "levelMin": 7,
    "ammoCount": 5,
    "tripleStar": 1,
    "doubleStar": 2,
    "singleStar": 3,
    "sceneId": 227
  },
  {
    "id": 228,
    "mode": 1,
    "levelMax": 23,
    "chapter": 4,
    "levelMin": 8,
    "ammoCount": 5,
    "tripleStar": 1,
    "doubleStar": 2,
    "singleStar": 3,
    "sceneId": 228
  },
  {
    "id": 229,
    "mode": 1,
    "levelMax": 23,
    "chapter": 4,
    "levelMin": 9,
    "ammoCount": 5,
    "tripleStar": 1,
    "doubleStar": 2,
    "singleStar": 3,
    "sceneId": 229
  },
  {
    "id": 230,
    "mode": 1,
    "levelMax": 23,
    "chapter": 4,
    "levelMin": 10,
    "ammoCount": 5,
    "tripleStar": 1,
    "doubleStar": 2,
    "singleStar": 3,
    "sceneId": 230
  },
  {
    "id": 231,
    "mode": 1,
    "levelMax": 24,
    "chapter": 4,
    "levelMin": 1,
    "ammoCount": 5,
    "tripleStar": 1,
    "doubleStar": 2,
    "singleStar": 3,
    "sceneId": 231
  },
  {
    "id": 232,
    "mode": 1,
    "levelMax": 24,
    "chapter": 4,
    "levelMin": 2,
    "ammoCount": 6,
    "tripleStar": 2,
    "doubleStar": 3,
    "singleStar": 4,
    "sceneId": 232
  },
  {
    "id": 233,
    "mode": 1,
    "levelMax": 24,
    "chapter": 4,
    "levelMin": 3,
    "ammoCount": 5,
    "tripleStar": 1,
    "doubleStar": 2,
    "singleStar": 3,
    "sceneId": 233
  },
  {
    "id": 234,
    "mode": 1,
    "levelMax": 24,
    "chapter": 4,
    "levelMin": 4,
    "ammoCount": 5,
    "tripleStar": 1,
    "doubleStar": 2,
    "singleStar": 3,
    "sceneId": 234
  },
  {
    "id": 235,
    "mode": 1,
    "levelMax": 24,
    "chapter": 4,
    "levelMin": 5,
    "ammoCount": 5,
    "tripleStar": 1,
    "doubleStar": 2,
    "singleStar": 3,
    "sceneId": 235
  },
  {
    "id": 236,
    "mode": 1,
    "levelMax": 24,
    "chapter": 4,
    "levelMin": 6,
    "ammoCount": 5,
    "tripleStar": 1,
    "doubleStar": 2,
    "singleStar": 3,
    "sceneId": 236
  },
  {
    "id": 237,
    "mode": 1,
    "levelMax": 24,
    "chapter": 4,
    "levelMin": 7,
    "ammoCount": 5,
    "tripleStar": 1,
    "doubleStar": 2,
    "singleStar": 3,
    "sceneId": 237
  },
  {
    "id": 238,
    "mode": 1,
    "levelMax": 24,
    "chapter": 4,
    "levelMin": 8,
    "ammoCount": 5,
    "tripleStar": 1,
    "doubleStar": 2,
    "singleStar": 3,
    "sceneId": 238
  },
  {
    "id": 239,
    "mode": 1,
    "levelMax": 24,
    "chapter": 4,
    "levelMin": 9,
    "ammoCount": 6,
    "tripleStar": 2,
    "doubleStar": 3,
    "singleStar": 4,
    "sceneId": 239
  },
  {
    "id": 240,
    "mode": 1,
    "levelMax": 24,
    "chapter": 4,
    "levelMin": 10,
    "ammoCount": 5,
    "tripleStar": 1,
    "doubleStar": 2,
    "singleStar": 3,
    "sceneId": 240
  },
  {
    "id": 241,
    "mode": 1,
    "levelMax": 25,
    "chapter": 4,
    "levelMin": 1,
    "ammoCount": 6,
    "tripleStar": 2,
    "doubleStar": 3,
    "singleStar": 4,
    "sceneId": 241
  },
  {
    "id": 242,
    "mode": 1,
    "levelMax": 25,
    "chapter": 4,
    "levelMin": 2,
    "ammoCount": 5,
    "tripleStar": 1,
    "doubleStar": 2,
    "singleStar": 3,
    "sceneId": 242
  },
  {
    "id": 243,
    "mode": 1,
    "levelMax": 25,
    "chapter": 4,
    "levelMin": 3,
    "ammoCount": 5,
    "tripleStar": 1,
    "doubleStar": 2,
    "singleStar": 3,
    "sceneId": 243
  },
  {
    "id": 244,
    "mode": 1,
    "levelMax": 25,
    "chapter": 4,
    "levelMin": 4,
    "ammoCount": 5,
    "tripleStar": 1,
    "doubleStar": 2,
    "singleStar": 3,
    "sceneId": 244
  },
  {
    "id": 245,
    "mode": 1,
    "levelMax": 25,
    "chapter": 4,
    "levelMin": 5,
    "ammoCount": 6,
    "tripleStar": 2,
    "doubleStar": 3,
    "singleStar": 4,
    "sceneId": 245
  },
  {
    "id": 1,
    "mode": 2,
    "levelMax": 1,
    "chapter": 1,
    "levelMin": 1,
    "ammoCount": 5,
    "tripleStar": 1,
    "doubleStar": 2,
    "singleStar": 3,
    "sceneId": 1
  },
  {
    "id": 2,
    "mode": 2,
    "levelMax": 1,
    "chapter": 1,
    "levelMin": 2,
    "ammoCount": 5,
    "tripleStar": 1,
    "doubleStar": 2,
    "singleStar": 3,
    "sceneId": 2
  },
  {
    "id": 3,
    "mode": 2,
    "levelMax": 1,
    "chapter": 1,
    "levelMin": 3,
    "ammoCount": 5,
    "tripleStar": 1,
    "doubleStar": 2,
    "singleStar": 3,
    "sceneId": 3
  },
  {
    "id": 4,
    "mode": 2,
    "levelMax": 1,
    "chapter": 1,
    "levelMin": 4,
    "ammoCount": 5,
    "tripleStar": 1,
    "doubleStar": 2,
    "singleStar": 3,
    "sceneId": 4
  },
  {
    "id": 5,
    "mode": 2,
    "levelMax": 1,
    "chapter": 1,
    "levelMin": 5,
    "ammoCount": 5,
    "tripleStar": 1,
    "doubleStar": 2,
    "singleStar": 3,
    "sceneId": 5
  },
  {
    "id": 6,
    "mode": 2,
    "levelMax": 1,
    "chapter": 1,
    "levelMin": 6,
    "ammoCount": 5,
    "tripleStar": 1,
    "doubleStar": 2,
    "singleStar": 3,
    "sceneId": 6
  },
  {
    "id": 7,
    "mode": 2,
    "levelMax": 1,
    "chapter": 1,
    "levelMin": 7,
    "ammoCount": 5,
    "tripleStar": 1,
    "doubleStar": 2,
    "singleStar": 3,
    "sceneId": 7
  },
  {
    "id": 8,
    "mode": 2,
    "levelMax": 1,
    "chapter": 1,
    "levelMin": 8,
    "ammoCount": 5,
    "tripleStar": 1,
    "doubleStar": 2,
    "singleStar": 3,
    "sceneId": 8
  },
  {
    "id": 9,
    "mode": 2,
    "levelMax": 1,
    "chapter": 1,
    "levelMin": 9,
    "ammoCount": 7,
    "tripleStar": 4,
    "doubleStar": 5,
    "singleStar": 6,
    "sceneId": 9
  },
  {
    "id": 10,
    "mode": 2,
    "levelMax": 1,
    "chapter": 1,
    "levelMin": 10,
    "ammoCount": 5,
    "tripleStar": 1,
    "doubleStar": 2,
    "singleStar": 3,
    "sceneId": 10
  },
  {
    "id": 11,
    "mode": 2,
    "levelMax": 2,
    "chapter": 1,
    "levelMin": 1,
    "ammoCount": 5,
    "tripleStar": 1,
    "doubleStar": 2,
    "singleStar": 3,
    "sceneId": 11
  },
  {
    "id": 12,
    "mode": 2,
    "levelMax": 2,
    "chapter": 1,
    "levelMin": 2,
    "ammoCount": 5,
    "tripleStar": 1,
    "doubleStar": 2,
    "singleStar": 3,
    "sceneId": 12
  },
  {
    "id": 13,
    "mode": 2,
    "levelMax": 2,
    "chapter": 1,
    "levelMin": 3,
    "ammoCount": 5,
    "tripleStar": 1,
    "doubleStar": 2,
    "singleStar": 3,
    "sceneId": 13
  },
  {
    "id": 14,
    "mode": 2,
    "levelMax": 2,
    "chapter": 1,
    "levelMin": 4,
    "ammoCount": 5,
    "tripleStar": 1,
    "doubleStar": 2,
    "singleStar": 3,
    "sceneId": 14
  },
  {
    "id": 15,
    "mode": 2,
    "levelMax": 2,
    "chapter": 1,
    "levelMin": 5,
    "ammoCount": 5,
    "tripleStar": 1,
    "doubleStar": 2,
    "singleStar": 3,
    "sceneId": 15
  },
  {
    "id": 16,
    "mode": 2,
    "levelMax": 2,
    "chapter": 1,
    "levelMin": 6,
    "ammoCount": 5,
    "tripleStar": 1,
    "doubleStar": 2,
    "singleStar": 3,
    "sceneId": 16
  },
  {
    "id": 17,
    "mode": 2,
    "levelMax": 2,
    "chapter": 1,
    "levelMin": 7,
    "ammoCount": 5,
    "tripleStar": 1,
    "doubleStar": 2,
    "singleStar": 3,
    "sceneId": 17
  },
  {
    "id": 18,
    "mode": 2,
    "levelMax": 2,
    "chapter": 1,
    "levelMin": 8,
    "ammoCount": 5,
    "tripleStar": 1,
    "doubleStar": 2,
    "singleStar": 3,
    "sceneId": 18
  },
  {
    "id": 19,
    "mode": 2,
    "levelMax": 2,
    "chapter": 1,
    "levelMin": 9,
    "ammoCount": 5,
    "tripleStar": 1,
    "doubleStar": 2,
    "singleStar": 3,
    "sceneId": 19
  },
  {
    "id": 20,
    "mode": 2,
    "levelMax": 2,
    "chapter": 1,
    "levelMin": 10,
    "ammoCount": 5,
    "tripleStar": 1,
    "doubleStar": 2,
    "singleStar": 3,
    "sceneId": 20
  },
  {
    "id": 21,
    "mode": 2,
    "levelMax": 3,
    "chapter": 2,
    "levelMin": 1,
    "ammoCount": 5,
    "tripleStar": 1,
    "doubleStar": 2,
    "singleStar": 3,
    "sceneId": 21
  },
  {
    "id": 22,
    "mode": 2,
    "levelMax": 3,
    "chapter": 2,
    "levelMin": 2,
    "ammoCount": 5,
    "tripleStar": 1,
    "doubleStar": 2,
    "singleStar": 3,
    "sceneId": 22
  },
  {
    "id": 23,
    "mode": 2,
    "levelMax": 3,
    "chapter": 2,
    "levelMin": 3,
    "ammoCount": 5,
    "tripleStar": 1,
    "doubleStar": 2,
    "singleStar": 3,
    "sceneId": 23
  },
  {
    "id": 24,
    "mode": 2,
    "levelMax": 3,
    "chapter": 2,
    "levelMin": 4,
    "ammoCount": 5,
    "tripleStar": 1,
    "doubleStar": 2,
    "singleStar": 3,
    "sceneId": 24
  },
  {
    "id": 25,
    "mode": 2,
    "levelMax": 3,
    "chapter": 2,
    "levelMin": 5,
    "ammoCount": 6,
    "tripleStar": 2,
    "doubleStar": 3,
    "singleStar": 4,
    "sceneId": 25
  },
  {
    "id": 26,
    "mode": 2,
    "levelMax": 3,
    "chapter": 2,
    "levelMin": 6,
    "ammoCount": 5,
    "tripleStar": 1,
    "doubleStar": 2,
    "singleStar": 3,
    "sceneId": 26
  },
  {
    "id": 27,
    "mode": 2,
    "levelMax": 3,
    "chapter": 2,
    "levelMin": 7,
    "ammoCount": 5,
    "tripleStar": 1,
    "doubleStar": 2,
    "singleStar": 3,
    "sceneId": 27
  },
  {
    "id": 28,
    "mode": 2,
    "levelMax": 3,
    "chapter": 2,
    "levelMin": 8,
    "ammoCount": 5,
    "tripleStar": 1,
    "doubleStar": 2,
    "singleStar": 3,
    "sceneId": 28
  },
  {
    "id": 29,
    "mode": 2,
    "levelMax": 3,
    "chapter": 2,
    "levelMin": 9,
    "ammoCount": 5,
    "tripleStar": 1,
    "doubleStar": 2,
    "singleStar": 3,
    "sceneId": 29
  },
  {
    "id": 30,
    "mode": 2,
    "levelMax": 3,
    "chapter": 2,
    "levelMin": 10,
    "ammoCount": 5,
    "tripleStar": 1,
    "doubleStar": 2,
    "singleStar": 3,
    "sceneId": 30
  },
  {
    "id": 31,
    "mode": 2,
    "levelMax": 4,
    "chapter": 2,
    "levelMin": 1,
    "ammoCount": 5,
    "tripleStar": 1,
    "doubleStar": 2,
    "singleStar": 3,
    "sceneId": 31
  },
  {
    "id": 32,
    "mode": 2,
    "levelMax": 4,
    "chapter": 2,
    "levelMin": 2,
    "ammoCount": 5,
    "tripleStar": 1,
    "doubleStar": 2,
    "singleStar": 3,
    "sceneId": 32
  },
  {
    "id": 33,
    "mode": 2,
    "levelMax": 4,
    "chapter": 2,
    "levelMin": 3,
    "ammoCount": 5,
    "tripleStar": 1,
    "doubleStar": 2,
    "singleStar": 3,
    "sceneId": 33
  },
  {
    "id": 34,
    "mode": 2,
    "levelMax": 4,
    "chapter": 2,
    "levelMin": 4,
    "ammoCount": 5,
    "tripleStar": 1,
    "doubleStar": 2,
    "singleStar": 3,
    "sceneId": 34
  },
  {
    "id": 35,
    "mode": 2,
    "levelMax": 4,
    "chapter": 2,
    "levelMin": 5,
    "ammoCount": 5,
    "tripleStar": 1,
    "doubleStar": 2,
    "singleStar": 3,
    "sceneId": 35
  },
  {
    "id": 36,
    "mode": 2,
    "levelMax": 4,
    "chapter": 2,
    "levelMin": 6,
    "ammoCount": 5,
    "tripleStar": 1,
    "doubleStar": 2,
    "singleStar": 3,
    "sceneId": 36
  },
  {
    "id": 37,
    "mode": 2,
    "levelMax": 4,
    "chapter": 2,
    "levelMin": 7,
    "ammoCount": 5,
    "tripleStar": 1,
    "doubleStar": 2,
    "singleStar": 3,
    "sceneId": 37
  },
  {
    "id": 38,
    "mode": 2,
    "levelMax": 4,
    "chapter": 2,
    "levelMin": 8,
    "ammoCount": 6,
    "tripleStar": 2,
    "doubleStar": 3,
    "singleStar": 4,
    "sceneId": 38
  },
  {
    "id": 39,
    "mode": 2,
    "levelMax": 4,
    "chapter": 2,
    "levelMin": 9,
    "ammoCount": 5,
    "tripleStar": 1,
    "doubleStar": 2,
    "singleStar": 3,
    "sceneId": 39
  },
  {
    "id": 40,
    "mode": 2,
    "levelMax": 4,
    "chapter": 2,
    "levelMin": 10,
    "ammoCount": 5,
    "tripleStar": 1,
    "doubleStar": 2,
    "singleStar": 3,
    "sceneId": 40
  },
  {
    "id": 41,
    "mode": 2,
    "levelMax": 5,
    "chapter": 3,
    "levelMin": 1,
    "ammoCount": 5,
    "tripleStar": 1,
    "doubleStar": 2,
    "singleStar": 3,
    "sceneId": 41
  },
  {
    "id": 42,
    "mode": 2,
    "levelMax": 5,
    "chapter": 3,
    "levelMin": 2,
    "ammoCount": 5,
    "tripleStar": 1,
    "doubleStar": 2,
    "singleStar": 3,
    "sceneId": 42
  },
  {
    "id": 43,
    "mode": 2,
    "levelMax": 5,
    "chapter": 3,
    "levelMin": 3,
    "ammoCount": 5,
    "tripleStar": 1,
    "doubleStar": 2,
    "singleStar": 3,
    "sceneId": 43
  },
  {
    "id": 44,
    "mode": 2,
    "levelMax": 5,
    "chapter": 3,
    "levelMin": 4,
    "ammoCount": 5,
    "tripleStar": 1,
    "doubleStar": 2,
    "singleStar": 3,
    "sceneId": 44
  },
  {
    "id": 45,
    "mode": 2,
    "levelMax": 5,
    "chapter": 3,
    "levelMin": 5,
    "ammoCount": 5,
    "tripleStar": 1,
    "doubleStar": 2,
    "singleStar": 3,
    "sceneId": 45
  },
  {
    "id": 46,
    "mode": 2,
    "levelMax": 5,
    "chapter": 3,
    "levelMin": 6,
    "ammoCount": 5,
    "tripleStar": 1,
    "doubleStar": 2,
    "singleStar": 3,
    "sceneId": 46
  },
  {
    "id": 47,
    "mode": 2,
    "levelMax": 5,
    "chapter": 3,
    "levelMin": 7,
    "ammoCount": 5,
    "tripleStar": 1,
    "doubleStar": 2,
    "singleStar": 3,
    "sceneId": 47
  },
  {
    "id": 48,
    "mode": 2,
    "levelMax": 5,
    "chapter": 3,
    "levelMin": 8,
    "ammoCount": 5,
    "tripleStar": 1,
    "doubleStar": 2,
    "singleStar": 3,
    "sceneId": 48
  },
  {
    "id": 49,
    "mode": 2,
    "levelMax": 5,
    "chapter": 3,
    "levelMin": 9,
    "ammoCount": 5,
    "tripleStar": 1,
    "doubleStar": 2,
    "singleStar": 3,
    "sceneId": 49
  },
  {
    "id": 50,
    "mode": 2,
    "levelMax": 5,
    "chapter": 3,
    "levelMin": 10,
    "ammoCount": 5,
    "tripleStar": 1,
    "doubleStar": 2,
    "singleStar": 3,
    "sceneId": 50
  },
  {
    "id": 51,
    "mode": 2,
    "levelMax": 6,
    "chapter": 3,
    "levelMin": 1,
    "ammoCount": 5,
    "tripleStar": 1,
    "doubleStar": 2,
    "singleStar": 3,
    "sceneId": 51
  },
  {
    "id": 52,
    "mode": 2,
    "levelMax": 6,
    "chapter": 3,
    "levelMin": 2,
    "ammoCount": 5,
    "tripleStar": 1,
    "doubleStar": 2,
    "singleStar": 3,
    "sceneId": 52
  },
  {
    "id": 53,
    "mode": 2,
    "levelMax": 6,
    "chapter": 3,
    "levelMin": 3,
    "ammoCount": 5,
    "tripleStar": 1,
    "doubleStar": 2,
    "singleStar": 3,
    "sceneId": 53
  },
  {
    "id": 54,
    "mode": 2,
    "levelMax": 6,
    "chapter": 3,
    "levelMin": 4,
    "ammoCount": 5,
    "tripleStar": 1,
    "doubleStar": 2,
    "singleStar": 3,
    "sceneId": 54
  },
  {
    "id": 55,
    "mode": 2,
    "levelMax": 6,
    "chapter": 3,
    "levelMin": 5,
    "ammoCount": 5,
    "tripleStar": 1,
    "doubleStar": 2,
    "singleStar": 3,
    "sceneId": 55
  },
  {
    "id": 56,
    "mode": 2,
    "levelMax": 6,
    "chapter": 3,
    "levelMin": 6,
    "ammoCount": 5,
    "tripleStar": 1,
    "doubleStar": 2,
    "singleStar": 3,
    "sceneId": 56
  },
  {
    "id": 57,
    "mode": 2,
    "levelMax": 6,
    "chapter": 3,
    "levelMin": 7,
    "ammoCount": 5,
    "tripleStar": 1,
    "doubleStar": 2,
    "singleStar": 3,
    "sceneId": 57
  },
  {
    "id": 58,
    "mode": 2,
    "levelMax": 6,
    "chapter": 3,
    "levelMin": 8,
    "ammoCount": 5,
    "tripleStar": 1,
    "doubleStar": 2,
    "singleStar": 3,
    "sceneId": 58
  },
  {
    "id": 59,
    "mode": 2,
    "levelMax": 6,
    "chapter": 3,
    "levelMin": 9,
    "ammoCount": 5,
    "tripleStar": 1,
    "doubleStar": 2,
    "singleStar": 3,
    "sceneId": 59
  },
  {
    "id": 60,
    "mode": 2,
    "levelMax": 6,
    "chapter": 3,
    "levelMin": 10,
    "ammoCount": 5,
    "tripleStar": 1,
    "doubleStar": 2,
    "singleStar": 3,
    "sceneId": 60
  },
  {
    "id": 61,
    "mode": 2,
    "levelMax": 7,
    "chapter": 3,
    "levelMin": 1,
    "ammoCount": 5,
    "tripleStar": 1,
    "doubleStar": 2,
    "singleStar": 3,
    "sceneId": 61
  },
  {
    "id": 62,
    "mode": 2,
    "levelMax": 7,
    "chapter": 3,
    "levelMin": 2,
    "ammoCount": 5,
    "tripleStar": 1,
    "doubleStar": 2,
    "singleStar": 3,
    "sceneId": 62
  },
  {
    "id": 63,
    "mode": 2,
    "levelMax": 7,
    "chapter": 3,
    "levelMin": 3,
    "ammoCount": 5,
    "tripleStar": 1,
    "doubleStar": 2,
    "singleStar": 3,
    "sceneId": 63
  },
  {
    "id": 64,
    "mode": 2,
    "levelMax": 7,
    "chapter": 3,
    "levelMin": 4,
    "ammoCount": 5,
    "tripleStar": 1,
    "doubleStar": 2,
    "singleStar": 3,
    "sceneId": 64
  },
  {
    "id": 65,
    "mode": 2,
    "levelMax": 7,
    "chapter": 3,
    "levelMin": 5,
    "ammoCount": 5,
    "tripleStar": 1,
    "doubleStar": 2,
    "singleStar": 3,
    "sceneId": 65
  },
  {
    "id": 66,
    "mode": 2,
    "levelMax": 7,
    "chapter": 3,
    "levelMin": 6,
    "ammoCount": 5,
    "tripleStar": 1,
    "doubleStar": 2,
    "singleStar": 3,
    "sceneId": 66
  },
  {
    "id": 67,
    "mode": 2,
    "levelMax": 7,
    "chapter": 3,
    "levelMin": 7,
    "ammoCount": 5,
    "tripleStar": 1,
    "doubleStar": 2,
    "singleStar": 3,
    "sceneId": 67
  },
  {
    "id": 68,
    "mode": 2,
    "levelMax": 7,
    "chapter": 3,
    "levelMin": 8,
    "ammoCount": 5,
    "tripleStar": 1,
    "doubleStar": 2,
    "singleStar": 3,
    "sceneId": 68
  },
  {
    "id": 69,
    "mode": 2,
    "levelMax": 7,
    "chapter": 3,
    "levelMin": 9,
    "ammoCount": 5,
    "tripleStar": 1,
    "doubleStar": 2,
    "singleStar": 3,
    "sceneId": 69
  },
  {
    "id": 70,
    "mode": 2,
    "levelMax": 7,
    "chapter": 3,
    "levelMin": 10,
    "ammoCount": 5,
    "tripleStar": 1,
    "doubleStar": 2,
    "singleStar": 3,
    "sceneId": 70
  },
  {
    "id": 71,
    "mode": 2,
    "levelMax": 8,
    "chapter": 3,
    "levelMin": 1,
    "ammoCount": 5,
    "tripleStar": 1,
    "doubleStar": 2,
    "singleStar": 3,
    "sceneId": 71
  },
  {
    "id": 72,
    "mode": 2,
    "levelMax": 8,
    "chapter": 3,
    "levelMin": 2,
    "ammoCount": 5,
    "tripleStar": 1,
    "doubleStar": 2,
    "singleStar": 3,
    "sceneId": 72
  },
  {
    "id": 73,
    "mode": 2,
    "levelMax": 8,
    "chapter": 3,
    "levelMin": 3,
    "ammoCount": 5,
    "tripleStar": 1,
    "doubleStar": 2,
    "singleStar": 3,
    "sceneId": 73
  },
  {
    "id": 74,
    "mode": 2,
    "levelMax": 8,
    "chapter": 3,
    "levelMin": 4,
    "ammoCount": 5,
    "tripleStar": 1,
    "doubleStar": 2,
    "singleStar": 3,
    "sceneId": 74
  },
  {
    "id": 75,
    "mode": 2,
    "levelMax": 8,
    "chapter": 3,
    "levelMin": 5,
    "ammoCount": 5,
    "tripleStar": 1,
    "doubleStar": 2,
    "singleStar": 3,
    "sceneId": 75
  },
  {
    "id": 76,
    "mode": 2,
    "levelMax": 8,
    "chapter": 3,
    "levelMin": 5,
    "ammoCount": 5,
    "tripleStar": 1,
    "doubleStar": 2,
    "singleStar": 3,
    "sceneId": 76
  },
  {
    "id": 77,
    "mode": 2,
    "levelMax": 8,
    "chapter": 3,
    "levelMin": 5,
    "ammoCount": 5,
    "tripleStar": 1,
    "doubleStar": 2,
    "singleStar": 3,
    "sceneId": 77
  },
  {
    "id": 78,
    "mode": 2,
    "levelMax": 8,
    "chapter": 3,
    "levelMin": 5,
    "ammoCount": 5,
    "tripleStar": 1,
    "doubleStar": 2,
    "singleStar": 3,
    "sceneId": 78
  },
  {
    "id": 79,
    "mode": 2,
    "levelMax": 8,
    "chapter": 3,
    "levelMin": 5,
    "ammoCount": 5,
    "tripleStar": 1,
    "doubleStar": 2,
    "singleStar": 3,
    "sceneId": 79
  },
  {
    "id": 80,
    "mode": 2,
    "levelMax": 8,
    "chapter": 3,
    "levelMin": 5,
    "ammoCount": 6,
    "tripleStar": 2,
    "doubleStar": 3,
    "singleStar": 4,
    "sceneId": 80
  },
  {
    "id": 81,
    "mode": 2,
    "levelMax": 9,
    "chapter": 3,
    "levelMin": 5,
    "ammoCount": 5,
    "tripleStar": 1,
    "doubleStar": 2,
    "singleStar": 3,
    "sceneId": 81
  },
  {
    "id": 82,
    "mode": 2,
    "levelMax": 9,
    "chapter": 3,
    "levelMin": 5,
    "ammoCount": 5,
    "tripleStar": 1,
    "doubleStar": 2,
    "singleStar": 3,
    "sceneId": 82
  },
  {
    "id": 83,
    "mode": 2,
    "levelMax": 9,
    "chapter": 3,
    "levelMin": 5,
    "ammoCount": 5,
    "tripleStar": 1,
    "doubleStar": 2,
    "singleStar": 3,
    "sceneId": 83
  },
  {
    "id": 84,
    "mode": 2,
    "levelMax": 9,
    "chapter": 3,
    "levelMin": 5,
    "ammoCount": 5,
    "tripleStar": 1,
    "doubleStar": 2,
    "singleStar": 3,
    "sceneId": 84
  },
  {
    "id": 85,
    "mode": 2,
    "levelMax": 9,
    "chapter": 3,
    "levelMin": 5,
    "ammoCount": 5,
    "tripleStar": 1,
    "doubleStar": 2,
    "singleStar": 3,
    "sceneId": 85
  },
  {
    "id": 86,
    "mode": 2,
    "levelMax": 9,
    "chapter": 3,
    "levelMin": 5,
    "ammoCount": 5,
    "tripleStar": 1,
    "doubleStar": 2,
    "singleStar": 3,
    "sceneId": 86
  },
  {
    "id": 87,
    "mode": 2,
    "levelMax": 9,
    "chapter": 3,
    "levelMin": 5,
    "ammoCount": 5,
    "tripleStar": 1,
    "doubleStar": 2,
    "singleStar": 3,
    "sceneId": 87
  },
  {
    "id": 88,
    "mode": 2,
    "levelMax": 9,
    "chapter": 3,
    "levelMin": 5,
    "ammoCount": 5,
    "tripleStar": 1,
    "doubleStar": 2,
    "singleStar": 3,
    "sceneId": 88
  },
  {
    "id": 89,
    "mode": 2,
    "levelMax": 9,
    "chapter": 3,
    "levelMin": 5,
    "ammoCount": 5,
    "tripleStar": 1,
    "doubleStar": 2,
    "singleStar": 3,
    "sceneId": 89
  },
  {
    "id": 90,
    "mode": 2,
    "levelMax": 9,
    "chapter": 3,
    "levelMin": 5,
    "ammoCount": 5,
    "tripleStar": 1,
    "doubleStar": 2,
    "singleStar": 3,
    "sceneId": 90
  },
  {
    "id": 91,
    "mode": 2,
    "levelMax": 10,
    "chapter": 3,
    "levelMin": 5,
    "ammoCount": 5,
    "tripleStar": 1,
    "doubleStar": 2,
    "singleStar": 3,
    "sceneId": 91
  },
  {
    "id": 92,
    "mode": 2,
    "levelMax": 10,
    "chapter": 3,
    "levelMin": 5,
    "ammoCount": 5,
    "tripleStar": 1,
    "doubleStar": 2,
    "singleStar": 3,
    "sceneId": 92
  },
  {
    "id": 93,
    "mode": 2,
    "levelMax": 10,
    "chapter": 3,
    "levelMin": 5,
    "ammoCount": 5,
    "tripleStar": 1,
    "doubleStar": 2,
    "singleStar": 3,
    "sceneId": 93
  },
  {
    "id": 1,
    "mode": 3,
    "levelMax": 1,
    "chapter": 1,
    "levelMin": 1,
    "ammoCount": 5,
    "tripleStar": 1,
    "doubleStar": 2,
    "singleStar": 3,
    "sceneId": 1
  },
  {
    "id": 2,
    "mode": 3,
    "levelMax": 1,
    "chapter": 1,
    "levelMin": 2,
    "ammoCount": 5,
    "tripleStar": 1,
    "doubleStar": 2,
    "singleStar": 3,
    "sceneId": 2
  },
  {
    "id": 3,
    "mode": 3,
    "levelMax": 1,
    "chapter": 1,
    "levelMin": 3,
    "ammoCount": 6,
    "tripleStar": 2,
    "doubleStar": 3,
    "singleStar": 4,
    "sceneId": 3
  },
  {
    "id": 4,
    "mode": 3,
    "levelMax": 1,
    "chapter": 1,
    "levelMin": 4,
    "ammoCount": 5,
    "tripleStar": 1,
    "doubleStar": 2,
    "singleStar": 3,
    "sceneId": 4
  },
  {
    "id": 5,
    "mode": 3,
    "levelMax": 1,
    "chapter": 1,
    "levelMin": 5,
    "ammoCount": 5,
    "tripleStar": 1,
    "doubleStar": 2,
    "singleStar": 3,
    "sceneId": 5
  },
  {
    "id": 6,
    "mode": 3,
    "levelMax": 1,
    "chapter": 1,
    "levelMin": 6,
    "ammoCount": 5,
    "tripleStar": 1,
    "doubleStar": 2,
    "singleStar": 3,
    "sceneId": 6
  },
  {
    "id": 7,
    "mode": 3,
    "levelMax": 1,
    "chapter": 1,
    "levelMin": 7,
    "ammoCount": 5,
    "tripleStar": 1,
    "doubleStar": 2,
    "singleStar": 3,
    "sceneId": 7
  },
  {
    "id": 8,
    "mode": 3,
    "levelMax": 1,
    "chapter": 1,
    "levelMin": 8,
    "ammoCount": 5,
    "tripleStar": 1,
    "doubleStar": 2,
    "singleStar": 3,
    "sceneId": 8
  },
  {
    "id": 9,
    "mode": 3,
    "levelMax": 1,
    "chapter": 1,
    "levelMin": 9,
    "ammoCount": 7,
    "tripleStar": 4,
    "doubleStar": 5,
    "singleStar": 6,
    "sceneId": 9
  },
  {
    "id": 10,
    "mode": 3,
    "levelMax": 1,
    "chapter": 1,
    "levelMin": 10,
    "ammoCount": 5,
    "tripleStar": 1,
    "doubleStar": 2,
    "singleStar": 3,
    "sceneId": 10
  },
  {
    "id": 11,
    "mode": 3,
    "levelMax": 2,
    "chapter": 1,
    "levelMin": 1,
    "ammoCount": 5,
    "tripleStar": 1,
    "doubleStar": 2,
    "singleStar": 3,
    "sceneId": 11
  },
  {
    "id": 12,
    "mode": 3,
    "levelMax": 2,
    "chapter": 1,
    "levelMin": 2,
    "ammoCount": 5,
    "tripleStar": 1,
    "doubleStar": 2,
    "singleStar": 3,
    "sceneId": 12
  },
  {
    "id": 13,
    "mode": 3,
    "levelMax": 2,
    "chapter": 1,
    "levelMin": 3,
    "ammoCount": 5,
    "tripleStar": 1,
    "doubleStar": 2,
    "singleStar": 3,
    "sceneId": 13
  },
  {
    "id": 14,
    "mode": 3,
    "levelMax": 2,
    "chapter": 1,
    "levelMin": 4,
    "ammoCount": 5,
    "tripleStar": 1,
    "doubleStar": 2,
    "singleStar": 3,
    "sceneId": 14
  },
  {
    "id": 15,
    "mode": 3,
    "levelMax": 2,
    "chapter": 1,
    "levelMin": 5,
    "ammoCount": 5,
    "tripleStar": 1,
    "doubleStar": 2,
    "singleStar": 3,
    "sceneId": 15
  },
  {
    "id": 16,
    "mode": 3,
    "levelMax": 2,
    "chapter": 1,
    "levelMin": 6,
    "ammoCount": 5,
    "tripleStar": 1,
    "doubleStar": 2,
    "singleStar": 3,
    "sceneId": 16
  },
  {
    "id": 17,
    "mode": 3,
    "levelMax": 2,
    "chapter": 1,
    "levelMin": 7,
    "ammoCount": 5,
    "tripleStar": 1,
    "doubleStar": 2,
    "singleStar": 3,
    "sceneId": 17
  },
  {
    "id": 18,
    "mode": 3,
    "levelMax": 2,
    "chapter": 1,
    "levelMin": 8,
    "ammoCount": 5,
    "tripleStar": 1,
    "doubleStar": 2,
    "singleStar": 3,
    "sceneId": 18
  },
  {
    "id": 19,
    "mode": 3,
    "levelMax": 2,
    "chapter": 1,
    "levelMin": 9,
    "ammoCount": 5,
    "tripleStar": 1,
    "doubleStar": 2,
    "singleStar": 3,
    "sceneId": 19
  },
  {
    "id": 20,
    "mode": 3,
    "levelMax": 2,
    "chapter": 1,
    "levelMin": 10,
    "ammoCount": 5,
    "tripleStar": 1,
    "doubleStar": 2,
    "singleStar": 3,
    "sceneId": 20
  },
  {
    "id": 21,
    "mode": 3,
    "levelMax": 3,
    "chapter": 2,
    "levelMin": 1,
    "ammoCount": 5,
    "tripleStar": 1,
    "doubleStar": 2,
    "singleStar": 3,
    "sceneId": 21
  },
  {
    "id": 22,
    "mode": 3,
    "levelMax": 3,
    "chapter": 2,
    "levelMin": 2,
    "ammoCount": 5,
    "tripleStar": 1,
    "doubleStar": 2,
    "singleStar": 3,
    "sceneId": 22
  },
  {
    "id": 23,
    "mode": 3,
    "levelMax": 3,
    "chapter": 2,
    "levelMin": 3,
    "ammoCount": 6,
    "tripleStar": 2,
    "doubleStar": 3,
    "singleStar": 4,
    "sceneId": 23
  },
  {
    "id": 24,
    "mode": 3,
    "levelMax": 3,
    "chapter": 2,
    "levelMin": 4,
    "ammoCount": 6,
    "tripleStar": 2,
    "doubleStar": 3,
    "singleStar": 4,
    "sceneId": 24
  },
  {
    "id": 25,
    "mode": 3,
    "levelMax": 3,
    "chapter": 2,
    "levelMin": 5,
    "ammoCount": 5,
    "tripleStar": 1,
    "doubleStar": 2,
    "singleStar": 3,
    "sceneId": 25
  },
  {
    "id": 26,
    "mode": 3,
    "levelMax": 3,
    "chapter": 2,
    "levelMin": 6,
    "ammoCount": 6,
    "tripleStar": 2,
    "doubleStar": 3,
    "singleStar": 4,
    "sceneId": 26
  },
  {
    "id": 27,
    "mode": 3,
    "levelMax": 3,
    "chapter": 2,
    "levelMin": 7,
    "ammoCount": 5,
    "tripleStar": 1,
    "doubleStar": 2,
    "singleStar": 3,
    "sceneId": 27
  },
  {
    "id": 28,
    "mode": 3,
    "levelMax": 3,
    "chapter": 2,
    "levelMin": 8,
    "ammoCount": 5,
    "tripleStar": 1,
    "doubleStar": 2,
    "singleStar": 3,
    "sceneId": 28
  },
  {
    "id": 29,
    "mode": 3,
    "levelMax": 3,
    "chapter": 2,
    "levelMin": 9,
    "ammoCount": 5,
    "tripleStar": 1,
    "doubleStar": 2,
    "singleStar": 3,
    "sceneId": 29
  },
  {
    "id": 30,
    "mode": 3,
    "levelMax": 3,
    "chapter": 2,
    "levelMin": 10,
    "ammoCount": 5,
    "tripleStar": 1,
    "doubleStar": 2,
    "singleStar": 3,
    "sceneId": 30
  },
  {
    "id": 1,
    "mode": 4,
    "levelMax": 1,
    "chapter": 1,
    "levelMin": 1,
    "ammoCount": 5,
    "tripleStar": 1,
    "doubleStar": 2,
    "singleStar": 3,
    "sceneId": 1
  },
  {
    "id": 2,
    "mode": 4,
    "levelMax": 1,
    "chapter": 1,
    "levelMin": 2,
    "ammoCount": 5,
    "tripleStar": 1,
    "doubleStar": 2,
    "singleStar": 3,
    "sceneId": 2
  },
  {
    "id": 3,
    "mode": 4,
    "levelMax": 1,
    "chapter": 1,
    "levelMin": 3,
    "ammoCount": 5,
    "tripleStar": 1,
    "doubleStar": 2,
    "singleStar": 3,
    "sceneId": 3
  },
  {
    "id": 4,
    "mode": 4,
    "levelMax": 1,
    "chapter": 1,
    "levelMin": 4,
    "ammoCount": 5,
    "tripleStar": 1,
    "doubleStar": 2,
    "singleStar": 3,
    "sceneId": 4
  },
  {
    "id": 5,
    "mode": 4,
    "levelMax": 1,
    "chapter": 1,
    "levelMin": 5,
    "ammoCount": 5,
    "tripleStar": 1,
    "doubleStar": 2,
    "singleStar": 3,
    "sceneId": 5
  },
  {
    "id": 6,
    "mode": 4,
    "levelMax": 1,
    "chapter": 1,
    "levelMin": 6,
    "ammoCount": 5,
    "tripleStar": 1,
    "doubleStar": 2,
    "singleStar": 3,
    "sceneId": 6
  },
  {
    "id": 7,
    "mode": 4,
    "levelMax": 1,
    "chapter": 1,
    "levelMin": 7,
    "ammoCount": 5,
    "tripleStar": 1,
    "doubleStar": 2,
    "singleStar": 3,
    "sceneId": 7
  },
  {
    "id": 8,
    "mode": 4,
    "levelMax": 1,
    "chapter": 1,
    "levelMin": 8,
    "ammoCount": 5,
    "tripleStar": 1,
    "doubleStar": 2,
    "singleStar": 3,
    "sceneId": 8
  },
  {
    "id": 9,
    "mode": 4,
    "levelMax": 1,
    "chapter": 1,
    "levelMin": 9,
    "ammoCount": 7,
    "tripleStar": 4,
    "doubleStar": 5,
    "singleStar": 6,
    "sceneId": 9
  },
  {
    "id": 10,
    "mode": 4,
    "levelMax": 1,
    "chapter": 1,
    "levelMin": 10,
    "ammoCount": 5,
    "tripleStar": 1,
    "doubleStar": 2,
    "singleStar": 3,
    "sceneId": 10
  },
  {
    "id": 11,
    "mode": 4,
    "levelMax": 2,
    "chapter": 1,
    "levelMin": 1,
    "ammoCount": 5,
    "tripleStar": 1,
    "doubleStar": 2,
    "singleStar": 3,
    "sceneId": 11
  },
  {
    "id": 12,
    "mode": 4,
    "levelMax": 2,
    "chapter": 1,
    "levelMin": 2,
    "ammoCount": 5,
    "tripleStar": 1,
    "doubleStar": 2,
    "singleStar": 3,
    "sceneId": 12
  },
  {
    "id": 13,
    "mode": 4,
    "levelMax": 2,
    "chapter": 1,
    "levelMin": 3,
    "ammoCount": 5,
    "tripleStar": 1,
    "doubleStar": 2,
    "singleStar": 3,
    "sceneId": 13
  },
  {
    "id": 14,
    "mode": 4,
    "levelMax": 2,
    "chapter": 1,
    "levelMin": 4,
    "ammoCount": 5,
    "tripleStar": 1,
    "doubleStar": 2,
    "singleStar": 3,
    "sceneId": 14
  },
  {
    "id": 15,
    "mode": 4,
    "levelMax": 2,
    "chapter": 1,
    "levelMin": 5,
    "ammoCount": 5,
    "tripleStar": 1,
    "doubleStar": 2,
    "singleStar": 3,
    "sceneId": 15
  },
  {
    "id": 16,
    "mode": 4,
    "levelMax": 2,
    "chapter": 1,
    "levelMin": 6,
    "ammoCount": 5,
    "tripleStar": 1,
    "doubleStar": 2,
    "singleStar": 3,
    "sceneId": 16
  },
  {
    "id": 17,
    "mode": 4,
    "levelMax": 2,
    "chapter": 1,
    "levelMin": 7,
    "ammoCount": 5,
    "tripleStar": 1,
    "doubleStar": 2,
    "singleStar": 3,
    "sceneId": 17
  },
  {
    "id": 18,
    "mode": 4,
    "levelMax": 2,
    "chapter": 1,
    "levelMin": 8,
    "ammoCount": 5,
    "tripleStar": 1,
    "doubleStar": 2,
    "singleStar": 3,
    "sceneId": 18
  },
  {
    "id": 19,
    "mode": 4,
    "levelMax": 2,
    "chapter": 1,
    "levelMin": 9,
    "ammoCount": 5,
    "tripleStar": 1,
    "doubleStar": 2,
    "singleStar": 3,
    "sceneId": 19
  },
  {
    "id": 20,
    "mode": 4,
    "levelMax": 2,
    "chapter": 1,
    "levelMin": 10,
    "ammoCount": 5,
    "tripleStar": 1,
    "doubleStar": 2,
    "singleStar": 3,
    "sceneId": 20
  },
  {
    "id": 21,
    "mode": 4,
    "levelMax": 3,
    "chapter": 2,
    "levelMin": 1,
    "ammoCount": 5,
    "tripleStar": 1,
    "doubleStar": 2,
    "singleStar": 3,
    "sceneId": 21
  },
  {
    "id": 22,
    "mode": 4,
    "levelMax": 3,
    "chapter": 2,
    "levelMin": 2,
    "ammoCount": 5,
    "tripleStar": 1,
    "doubleStar": 2,
    "singleStar": 3,
    "sceneId": 22
  },
  {
    "id": 23,
    "mode": 4,
    "levelMax": 3,
    "chapter": 2,
    "levelMin": 3,
    "ammoCount": 5,
    "tripleStar": 1,
    "doubleStar": 2,
    "singleStar": 3,
    "sceneId": 23
  },
  {
    "id": 24,
    "mode": 4,
    "levelMax": 3,
    "chapter": 2,
    "levelMin": 4,
    "ammoCount": 5,
    "tripleStar": 1,
    "doubleStar": 2,
    "singleStar": 3,
    "sceneId": 24
  },
  {
    "id": 25,
    "mode": 4,
    "levelMax": 3,
    "chapter": 2,
    "levelMin": 5,
    "ammoCount": 6,
    "tripleStar": 2,
    "doubleStar": 3,
    "singleStar": 4,
    "sceneId": 25
  },
  {
    "id": 26,
    "mode": 4,
    "levelMax": 3,
    "chapter": 2,
    "levelMin": 6,
    "ammoCount": 5,
    "tripleStar": 1,
    "doubleStar": 2,
    "singleStar": 3,
    "sceneId": 26
  },
  {
    "id": 27,
    "mode": 4,
    "levelMax": 3,
    "chapter": 2,
    "levelMin": 7,
    "ammoCount": 5,
    "tripleStar": 1,
    "doubleStar": 2,
    "singleStar": 3,
    "sceneId": 27
  },
  {
    "id": 28,
    "mode": 4,
    "levelMax": 3,
    "chapter": 2,
    "levelMin": 8,
    "ammoCount": 5,
    "tripleStar": 1,
    "doubleStar": 2,
    "singleStar": 3,
    "sceneId": 28
  },
  {
    "id": 29,
    "mode": 4,
    "levelMax": 3,
    "chapter": 2,
    "levelMin": 9,
    "ammoCount": 5,
    "tripleStar": 1,
    "doubleStar": 2,
    "singleStar": 3,
    "sceneId": 29
  },
  {
    "id": 30,
    "mode": 4,
    "levelMax": 3,
    "chapter": 2,
    "levelMin": 10,
    "ammoCount": 5,
    "tripleStar": 1,
    "doubleStar": 2,
    "singleStar": 3,
    "sceneId": 30
  },
  {
    "id": 31,
    "mode": 4,
    "levelMax": 4,
    "chapter": 2,
    "levelMin": 1,
    "ammoCount": 5,
    "tripleStar": 1,
    "doubleStar": 2,
    "singleStar": 3,
    "sceneId": 31
  },
  {
    "id": 32,
    "mode": 4,
    "levelMax": 4,
    "chapter": 2,
    "levelMin": 2,
    "ammoCount": 5,
    "tripleStar": 1,
    "doubleStar": 2,
    "singleStar": 3,
    "sceneId": 32
  },
  {
    "id": 33,
    "mode": 4,
    "levelMax": 4,
    "chapter": 2,
    "levelMin": 3,
    "ammoCount": 5,
    "tripleStar": 1,
    "doubleStar": 2,
    "singleStar": 3,
    "sceneId": 33
  },
  {
    "id": 34,
    "mode": 4,
    "levelMax": 4,
    "chapter": 2,
    "levelMin": 4,
    "ammoCount": 5,
    "tripleStar": 1,
    "doubleStar": 2,
    "singleStar": 3,
    "sceneId": 34
  },
  {
    "id": 35,
    "mode": 4,
    "levelMax": 4,
    "chapter": 2,
    "levelMin": 5,
    "ammoCount": 5,
    "tripleStar": 1,
    "doubleStar": 2,
    "singleStar": 3,
    "sceneId": 35
  },
  {
    "id": 36,
    "mode": 4,
    "levelMax": 4,
    "chapter": 2,
    "levelMin": 6,
    "ammoCount": 5,
    "tripleStar": 1,
    "doubleStar": 2,
    "singleStar": 3,
    "sceneId": 36
  },
  {
    "id": 37,
    "mode": 4,
    "levelMax": 4,
    "chapter": 2,
    "levelMin": 7,
    "ammoCount": 5,
    "tripleStar": 1,
    "doubleStar": 2,
    "singleStar": 3,
    "sceneId": 37
  },
  {
    "id": 38,
    "mode": 4,
    "levelMax": 4,
    "chapter": 2,
    "levelMin": 8,
    "ammoCount": 6,
    "tripleStar": 2,
    "doubleStar": 3,
    "singleStar": 4,
    "sceneId": 38
  },
  {
    "id": 39,
    "mode": 4,
    "levelMax": 4,
    "chapter": 2,
    "levelMin": 9,
    "ammoCount": 5,
    "tripleStar": 1,
    "doubleStar": 2,
    "singleStar": 3,
    "sceneId": 39
  },
  {
    "id": 40,
    "mode": 4,
    "levelMax": 4,
    "chapter": 2,
    "levelMin": 10,
    "ammoCount": 5,
    "tripleStar": 1,
    "doubleStar": 2,
    "singleStar": 3,
    "sceneId": 40
  },
  {
    "id": 41,
    "mode": 4,
    "levelMax": 5,
    "chapter": 3,
    "levelMin": 1,
    "ammoCount": 5,
    "tripleStar": 1,
    "doubleStar": 2,
    "singleStar": 3,
    "sceneId": 41
  },
  {
    "id": 42,
    "mode": 4,
    "levelMax": 5,
    "chapter": 3,
    "levelMin": 2,
    "ammoCount": 5,
    "tripleStar": 1,
    "doubleStar": 2,
    "singleStar": 3,
    "sceneId": 42
  },
  {
    "id": 43,
    "mode": 4,
    "levelMax": 5,
    "chapter": 3,
    "levelMin": 3,
    "ammoCount": 5,
    "tripleStar": 1,
    "doubleStar": 2,
    "singleStar": 3,
    "sceneId": 43
  },
  {
    "id": 44,
    "mode": 4,
    "levelMax": 5,
    "chapter": 3,
    "levelMin": 4,
    "ammoCount": 5,
    "tripleStar": 1,
    "doubleStar": 2,
    "singleStar": 3,
    "sceneId": 44
  },
  {
    "id": 45,
    "mode": 4,
    "levelMax": 5,
    "chapter": 3,
    "levelMin": 5,
    "ammoCount": 5,
    "tripleStar": 1,
    "doubleStar": 2,
    "singleStar": 3,
    "sceneId": 45
  },
  {
    "id": 46,
    "mode": 4,
    "levelMax": 5,
    "chapter": 3,
    "levelMin": 6,
    "ammoCount": 5,
    "tripleStar": 1,
    "doubleStar": 2,
    "singleStar": 3,
    "sceneId": 46
  },
  {
    "id": 47,
    "mode": 4,
    "levelMax": 5,
    "chapter": 3,
    "levelMin": 7,
    "ammoCount": 5,
    "tripleStar": 1,
    "doubleStar": 2,
    "singleStar": 3,
    "sceneId": 47
  },
  {
    "id": 48,
    "mode": 4,
    "levelMax": 5,
    "chapter": 3,
    "levelMin": 8,
    "ammoCount": 5,
    "tripleStar": 1,
    "doubleStar": 2,
    "singleStar": 3,
    "sceneId": 48
  },
  {
    "id": 49,
    "mode": 4,
    "levelMax": 5,
    "chapter": 3,
    "levelMin": 9,
    "ammoCount": 6,
    "tripleStar": 2,
    "doubleStar": 3,
    "singleStar": 4,
    "sceneId": 49
  },
  {
    "id": 50,
    "mode": 4,
    "levelMax": 5,
    "chapter": 3,
    "levelMin": 10,
    "ammoCount": 5,
    "tripleStar": 1,
    "doubleStar": 2,
    "singleStar": 3,
    "sceneId": 50
  },
  {
    "id": 51,
    "mode": 4,
    "levelMax": 6,
    "chapter": 3,
    "levelMin": 1,
    "ammoCount": 5,
    "tripleStar": 1,
    "doubleStar": 2,
    "singleStar": 3,
    "sceneId": 51
  },
  {
    "id": 52,
    "mode": 4,
    "levelMax": 6,
    "chapter": 3,
    "levelMin": 2,
    "ammoCount": 5,
    "tripleStar": 1,
    "doubleStar": 2,
    "singleStar": 3,
    "sceneId": 52
  },
  {
    "id": 53,
    "mode": 4,
    "levelMax": 6,
    "chapter": 3,
    "levelMin": 3,
    "ammoCount": 5,
    "tripleStar": 1,
    "doubleStar": 2,
    "singleStar": 3,
    "sceneId": 53
  },
  {
    "id": 54,
    "mode": 4,
    "levelMax": 6,
    "chapter": 3,
    "levelMin": 4,
    "ammoCount": 6,
    "tripleStar": 2,
    "doubleStar": 3,
    "singleStar": 4,
    "sceneId": 54
  },
  {
    "id": 55,
    "mode": 4,
    "levelMax": 6,
    "chapter": 3,
    "levelMin": 5,
    "ammoCount": 5,
    "tripleStar": 1,
    "doubleStar": 2,
    "singleStar": 3,
    "sceneId": 55
  },
  {
    "id": 56,
    "mode": 4,
    "levelMax": 6,
    "chapter": 3,
    "levelMin": 6,
    "ammoCount": 6,
    "tripleStar": 2,
    "doubleStar": 3,
    "singleStar": 4,
    "sceneId": 56
  },
  {
    "id": 57,
    "mode": 4,
    "levelMax": 6,
    "chapter": 3,
    "levelMin": 7,
    "ammoCount": 5,
    "tripleStar": 1,
    "doubleStar": 2,
    "singleStar": 3,
    "sceneId": 57
  },
  {
    "id": 58,
    "mode": 4,
    "levelMax": 6,
    "chapter": 3,
    "levelMin": 8,
    "ammoCount": 5,
    "tripleStar": 1,
    "doubleStar": 2,
    "singleStar": 3,
    "sceneId": 58
  },
  {
    "id": 59,
    "mode": 4,
    "levelMax": 6,
    "chapter": 3,
    "levelMin": 9,
    "ammoCount": 5,
    "tripleStar": 1,
    "doubleStar": 2,
    "singleStar": 3,
    "sceneId": 59
  },
  {
    "id": 60,
    "mode": 4,
    "levelMax": 6,
    "chapter": 3,
    "levelMin": 10,
    "ammoCount": 5,
    "tripleStar": 1,
    "doubleStar": 2,
    "singleStar": 3,
    "sceneId": 60
  },
  {
    "id": 61,
    "mode": 4,
    "levelMax": 7,
    "chapter": 3,
    "levelMin": 1,
    "ammoCount": 6,
    "tripleStar": 2,
    "doubleStar": 3,
    "singleStar": 4,
    "sceneId": 61
  },
  {
    "id": 62,
    "mode": 4,
    "levelMax": 7,
    "chapter": 3,
    "levelMin": 2,
    "ammoCount": 5,
    "tripleStar": 1,
    "doubleStar": 2,
    "singleStar": 3,
    "sceneId": 62
  },
  {
    "id": 63,
    "mode": 4,
    "levelMax": 7,
    "chapter": 3,
    "levelMin": 3,
    "ammoCount": 5,
    "tripleStar": 1,
    "doubleStar": 2,
    "singleStar": 3,
    "sceneId": 63
  },
  {
    "id": 64,
    "mode": 4,
    "levelMax": 7,
    "chapter": 3,
    "levelMin": 4,
    "ammoCount": 5,
    "tripleStar": 1,
    "doubleStar": 2,
    "singleStar": 3,
    "sceneId": 64
  },
  {
    "id": 65,
    "mode": 4,
    "levelMax": 7,
    "chapter": 3,
    "levelMin": 5,
    "ammoCount": 5,
    "tripleStar": 1,
    "doubleStar": 2,
    "singleStar": 3,
    "sceneId": 65
  },
  {
    "id": 66,
    "mode": 4,
    "levelMax": 7,
    "chapter": 3,
    "levelMin": 6,
    "ammoCount": 5,
    "tripleStar": 1,
    "doubleStar": 2,
    "singleStar": 3,
    "sceneId": 66
  },
  {
    "id": 67,
    "mode": 4,
    "levelMax": 7,
    "chapter": 3,
    "levelMin": 7,
    "ammoCount": 5,
    "tripleStar": 1,
    "doubleStar": 2,
    "singleStar": 3,
    "sceneId": 67
  },
  {
    "id": 68,
    "mode": 4,
    "levelMax": 7,
    "chapter": 3,
    "levelMin": 8,
    "ammoCount": 5,
    "tripleStar": 1,
    "doubleStar": 2,
    "singleStar": 3,
    "sceneId": 68
  },
  {
    "id": 69,
    "mode": 4,
    "levelMax": 7,
    "chapter": 3,
    "levelMin": 9,
    "ammoCount": 6,
    "tripleStar": 2,
    "doubleStar": 3,
    "singleStar": 4,
    "sceneId": 69
  },
  {
    "id": 70,
    "mode": 4,
    "levelMax": 7,
    "chapter": 3,
    "levelMin": 10,
    "ammoCount": 5,
    "tripleStar": 1,
    "doubleStar": 2,
    "singleStar": 3,
    "sceneId": 70
  },
  {
    "id": 71,
    "mode": 4,
    "levelMax": 8,
    "chapter": 3,
    "levelMin": 1,
    "ammoCount": 5,
    "tripleStar": 1,
    "doubleStar": 2,
    "singleStar": 3,
    "sceneId": 71
  },
  {
    "id": 72,
    "mode": 4,
    "levelMax": 8,
    "chapter": 3,
    "levelMin": 2,
    "ammoCount": 5,
    "tripleStar": 1,
    "doubleStar": 2,
    "singleStar": 3,
    "sceneId": 72
  },
  {
    "id": 73,
    "mode": 4,
    "levelMax": 8,
    "chapter": 3,
    "levelMin": 3,
    "ammoCount": 5,
    "tripleStar": 1,
    "doubleStar": 2,
    "singleStar": 3,
    "sceneId": 73
  },
  {
    "id": 74,
    "mode": 4,
    "levelMax": 8,
    "chapter": 3,
    "levelMin": 4,
    "ammoCount": 5,
    "tripleStar": 1,
    "doubleStar": 2,
    "singleStar": 3,
    "sceneId": 74
  },
  {
    "id": 75,
    "mode": 4,
    "levelMax": 8,
    "chapter": 3,
    "levelMin": 5,
    "ammoCount": 5,
    "tripleStar": 1,
    "doubleStar": 2,
    "singleStar": 3,
    "sceneId": 75
  }
]
